{"beethoven_opus90_2.mid": {"1.5": ["Piano-right_E4_0.25"], "1.75": ["Piano-right_F#4_0.25"], "2.0": ["Piano-right_E4_0.25", "Piano-right_G#4_1.0", "Piano-left_E2.E3_0.5"], "2.25": ["Piano-right_B3_0.25"], "2.5": ["Piano-right_E4_0.25"], "2.75": ["Piano-right_B3_0.25"], "3.0": ["Piano-right_G#4_0.25", "Piano-right_B4_0.5"], "3.25": ["Piano-right_B3_0.25"], "3.5": ["Piano-right_F#4_0.25", "Piano-right_A4_0.5"], "3.75": ["Piano-right_B3_0.25"], "4.0": ["Piano-right_E4_0.25", "Piano-right_G#4_0.5", "Piano-left_B1.B2_0.5"], "4.25": ["Piano-right_B3_0.25"], "4.5": ["Piano-right_E-4_0.25", "Piano-right_F#4_0.5"], "4.75": ["Piano-right_B3_0.25"], "5.0": ["Piano-right_E-4_0.25", "Piano-right_F#4_0.5"], "5.25": ["Piano-right_B3_0.25"], "5.5": ["Piano-right_E4_0.25", "Piano-right_G#4_0.5"], "5.75": ["Piano-right_B3_0.25"], "6.0": ["Piano-right_E4_0.25", "Piano-right_A4_0.5", "Piano-left_C#2.C#3_0.5"], "6.25": ["Piano-right_B3_0.25"], "6.5": ["Piano-right_E4_0.25", "Piano-right_C#5_0.5"], "6.75": ["Piano-right_B3_0.25"], "7.0": ["Piano-right_F#4_0.25", "Piano-right_B4_0.5", "Piano-left_E-3.E-2_0.5"], "7.25": ["Piano-right_B3_0.25"], "7.5": ["Piano-right_E-4_0.25", "Piano-right_F#4_0.5", "Piano-left_B2.B1_0.5"], "7.75": ["Piano-right_B3_0.25"], "8.0": ["Piano-right_B3.E4.G#4_1.0", "Piano-left_E2.E3_0.25"], "9.5": ["Piano-right_E5_0.25", "Piano-left_G#3_0.25"], "9.75": ["Piano-right_F#5_0.25", "Piano-left_F#3_0.25"], "10.0": ["Piano-right_G#4.G#5_1.0", "Piano-left_E3_0.25"], "11.0": ["Piano-right_B4.B5_0.5", "Piano-left_E3_0.25"], "11.5": ["Piano-right_A4.A5_0.5", "Piano-left_B2_0.25"], "12.0": ["Piano-right_G#4.G#5_0.5", "Piano-left_E-3_0.25"], "12.5": ["Piano-right_F#4.F#5_0.5", "Piano-left_B2_0.25"], "13.0": ["Piano-right_F#4.F#5_0.5", "Piano-left_E-3_0.25"], "13.5": ["Piano-right_G#4.G#5_0.5", "Piano-left_F3_0.25"], "14.0": ["Piano-right_A4.A5_0.5", "Piano-left_F#3_0.25"], "14.5": ["Piano-right_C#5.C#6_0.5", "Piano-left_A3_0.25"], "15.0": ["Piano-right_B4.B5_0.5", "Piano-left_G#3_0.25"], "15.5": ["Piano-right_E-6.E-5_0.5", "Piano-left_B2.F#3_0.25"], "16.0": ["Piano-right_E6.E5_1.0", "Piano-left_E3.G#3_0.25"], "17.5": ["Piano-right_B4_0.5", "Piano-left_F#3_0.25"], "18.0": ["Piano-right_B-4_1.0", "Piano-left_C#3_0.25"], "19.0": ["Piano-right_E5_1.0", "Piano-left_F#2_0.25"], "20.0": ["Piano-right_E-5_1.5", "Piano-left_B2_0.25"], "21.5": ["Piano-right_A4_0.5", "Piano-left_C#3_0.25"], "22.0": ["Piano-right_G#4_1.0", "Piano-left_B2_0.25"], "23.0": ["Piano-right_D5_1.0", "Piano-left_E2_0.25"], "24.0": ["Piano-right_C#5_1.5", "Piano-left_A2_0.25"], "25.5": ["Piano-right_C#5_0.5", "Piano-left_A2_0.25"], "26.0": ["Piano-right_C5_0.5", "Piano-left_A2_0.25"], "26.5": ["Piano-right_C#5_0.5", "Piano-left_A2_0.25"], "27.0": ["Piano-right_A4.E4.C#4_1/3", "Piano-left_A2_0.25"], "27.5": ["Piano-right_G#4.E4.B3_1/3", "Piano-left_B2_0.25"], "28.0": ["Piano-right_G#4_0.5", "Piano-right_E4.B-3_1.0", "Piano-left_C#3_0.25"], "28.5": ["Piano-right_F#4_1.0", "Piano-left_C#3_0.25"], "29.0": ["Piano-right_E4.A3_1.0", "Piano-left_C3_0.25"], "29.5": ["Piano-right_F#4_0.5", "Piano-left_C3_0.25"], "30.0": ["Piano-right_F#4.E-4.A3_0.5", "Piano-left_B2_0.25"], "30.5": ["Piano-right_B4_0.5", "Piano-right_E-4_1.0", "Piano-left_B2_0.25"], "31.0": ["Piano-right_B-4_0.5", "Piano-left_B2_0.25"], "31.5": ["Piano-right_B4.E-4_0.5", "Piano-left_B2_0.25"], "32.0": ["Piano-right_E4_1.0"], "33.5": ["Piano-right_B5.B4_0.5"], "34.0": ["Piano-right_B-5.B-4_1.0"], "35.0": ["Piano-right_E6.E5_1.0"], "36.0": ["Piano-right_E-6.E-5_1.5"], "37.5": ["Piano-right_A5.A4_0.5"], "38.0": ["Piano-right_G#5.G#4_1.0"], "39.0": ["Piano-right_D6.D5_1.0"], "40.0": ["Piano-right_C#6.C#5_1.5"], "41.5": ["Piano-right_C#6.C#5_0.5"], "42.0": ["Piano-right_C6.C5_0.5"], "42.5": ["Piano-right_C#6.C#5_0.5"], "43.0": ["Piano-right_A5.A4_1/3"], "43.5": ["Piano-right_G#5.G#4_1/3"], "44.0": ["Piano-right_G#5.G#4_0.5"], "44.5": ["Piano-right_F#5.F#4_1.0"], "45.5": ["Piano-right_F#5.F#4_0.5"], "46.0": ["Piano-right_F#5.F#4_0.5"], "46.5": ["Piano-right_B5.B4_0.5"], "47.0": ["Piano-right_B-5.B-4_0.5"], "47.5": ["Piano-right_B5.B4_0.5"], "48.0": ["Piano-right_E5.E4_1.0"], "49.5": ["Piano-right_E4_0.25"], "49.75": ["Piano-right_F#4_0.25"], "50.0": ["Piano-right_E4_0.25"], "8.25": ["Piano-left_G#3_0.25"], "8.5": ["Piano-left_B3_0.25"], "8.75": ["Piano-left_A3_0.25"], "9.0": ["Piano-left_G#3_0.25"], "9.25": ["Piano-left_A3_0.25"], "10.25": ["Piano-left_B3_0.25"], "10.5": ["Piano-left_B2_0.25"], "10.75": ["Piano-left_B3_0.25"], "11.25": ["Piano-left_B3_0.25"], "11.75": ["Piano-left_B3_0.25"], "12.25": ["Piano-left_B3_0.25"], "12.75": ["Piano-left_B3_0.25"], "13.25": ["Piano-left_B3_0.25"], "13.75": ["Piano-left_B3_0.25"], "14.25": ["Piano-left_B3_0.25"], "14.75": ["Piano-left_B3_0.25"], "15.25": ["Piano-left_B3_0.25"], "15.75": ["Piano-left_A3_0.25"], "16.25": ["Piano-left_B3_0.25"], "16.5": ["Piano-left_G#3_0.25"], "16.75": ["Piano-left_E3_0.25"], "17.0": ["Piano-left_E-3_0.25"], "17.25": ["Piano-left_B3_0.25"], "17.75": ["Piano-left_E-3_0.25"], "18.25": ["Piano-left_B-3_0.25"], "18.5": ["Piano-left_F#3_0.25"], "18.75": ["Piano-left_C#3_0.25"], "19.25": ["Piano-left_B-3_0.25"], "19.5": ["Piano-left_F#3_0.25"], "19.75": ["Piano-left_C#3_0.25"], "20.25": ["Piano-left_B3_0.25"], "20.5": ["Piano-left_F#3_0.25"], "20.75": ["Piano-left_E-3_0.25"], "21.0": ["Piano-left_B2_0.25"], "21.25": ["Piano-left_B3_0.25"], "21.75": ["Piano-left_A3_0.25"], "22.25": ["Piano-left_G#3_0.25"], "22.5": ["Piano-left_E3_0.25"], "22.75": ["Piano-left_B2_0.25"], "23.25": ["Piano-left_G#3_0.25"], "23.5": ["Piano-left_E3_0.25"], "23.75": ["Piano-left_B2_0.25"], "24.25": ["Piano-left_A3_0.25"], "24.5": ["Piano-left_E3_0.25"], "24.75": ["Piano-left_C#3_0.25"], "25.0": ["Piano-left_A2_0.25"], "25.25": ["Piano-left_E3_0.25"], "25.75": ["Piano-left_E3_0.25"], "26.25": ["Piano-left_E3_0.25"], "26.75": ["Piano-left_E3_0.25"], "27.25": ["Piano-left_E3_0.25"], "27.75": ["Piano-left_E3_0.25"], "28.25": ["Piano-left_E3_0.25"], "28.75": ["Piano-left_E3_0.25"], "29.25": ["Piano-left_E3_0.25"], "29.75": ["Piano-left_E3_0.25"], "30.25": ["Piano-left_F#3_0.25"], "30.75": ["Piano-left_F#3.A3_0.25"], "31.25": ["Piano-left_F#3.A3_0.25"]}, "beethoven_opus90_1.mid": {"2.0": ["Piano-right_G4.E4.B3.G3_0.25", "Piano-left_E3.E2_0.25"], "3.0": ["Piano-right_G3.B3.E4_2.0", "Piano-right_G4_1.5", "Piano-left_E2.E3_2.0"], "4.5": ["Piano-right_F#4_0.5"], "5.0": ["Piano-right_E4.G3_0.25", "Piano-left_E3.E2_0.25"], "6.0": ["Piano-right_A3.F#4.A4_0.5", "Piano-left_D2.D3_0.5"], "8.0": ["Piano-right_A4.F#4_1.0", "Piano-left_D4_1.0"], "9.0": ["Piano-right_F#4.A4_1.5", "Piano-left_C4.D4_1.5"], "10.5": ["Piano-right_G4_0.5", "Piano-left_D4.B3_0.5"], "11.0": ["Piano-right_A4.F#4_0.75", "Piano-left_A3.C4_0.75"], "12.0": ["Piano-right_B4.G4_0.75", "Piano-left_G3.B3_0.75"], "14.0": ["Piano-right_B4.G4.D4.B3_0.25", "Piano-left_G3.G2_0.25"], "15.0": ["Piano-right_D4.B3.G4_2.0", "Piano-right_B4_1.5", "Piano-left_G2.G3_2.0"], "16.5": ["Piano-right_A4_0.5"], "17.0": ["Piano-right_G4.B3_0.25", "Piano-left_G2.G1_0.25"], "18.0": ["Piano-right_C#4.B-4.C#5_0.5", "Piano-left_F#1.F#2_0.5"], "20.0": ["Piano-right_C#5.B-4_1.0", "Piano-left_F#4_1.0"], "21.0": ["Piano-right_B-4.C#5_1.5", "Piano-left_E4.F#4_1.5"], "22.5": ["Piano-right_B4_0.5", "Piano-left_F#4.D4_0.5"], "23.0": ["Piano-right_C#5.B-4_0.75", "Piano-left_C#4.E4_0.75"], "24.0": ["Piano-right_D5.B4_0.75", "Piano-left_B3.D4_0.75"], "26.0": ["Piano-right_D5_2.0"], "28.0": ["Piano-right_G5_1.0"], "29.0": ["Piano-right_E5_1.0", "Piano-left_E4_3.0"], "30.0": ["Piano-right_D5_1.0", "Piano-left_A3_2.0"], "31.0": ["Piano-right_C5_1.0"], "32.0": ["Piano-right_C5_2.0", "Piano-left_F#4_3.0", "Piano-left_E-4_1.0"], "34.0": ["Piano-right_A5_1.0"], "35.0": ["Piano-right_C5_2.0", "Piano-left_F#4_1.0"], "37.0": ["Piano-right_B4_1.0"], "38.0": ["Piano-right_B4_2.0", "Piano-left_G3_1.0"], "40.0": ["Piano-right_G4_1.0"], "41.0": ["Piano-right_G4_2.0", "Piano-left_E4_1.0"], "43.0": ["Piano-right_E4_1.0"], "44.0": ["Piano-right_E4_2.0", "Piano-left_C3_4.0"], "46.0": ["Piano-right_G3_1.0"], "47.0": ["Piano-right_E3_1.0"], "48.0": ["Piano-right_E-3.B3_1.75", "Piano-left_B2.B1_1.75"], "50.0": ["Piano-right_E5.E6_2.5"], "52.5": ["Piano-right_E-5.E-6_0.5"], "53.0": ["Piano-right_E5.E6_1.0"], "54.0": ["Piano-right_C4.E4.F#4_2.0", "Piano-left_A2_2.0"], "56.0": ["Piano-right_F#4.E4.C#4_1.0", "Piano-left_B-2_1.0"], "57.0": ["Piano-right_A3.E-4_3.0", "Piano-right_F#4_1.5", "Piano-left_B2_3.0"], "58.5": ["Piano-right_G4_0.5"], "59.0": ["Piano-right_A4_0.5"], "59.5": ["Piano-right_G4_0.5"], "60.0": ["Piano-right_F#4_1.0", "Piano-left_G3.C3_2.0"], "61.0": ["Piano-right_E4_1.0"], "62.0": ["Piano-right_E5.E6_2.5", "Piano-left_B2_0.5"], "64.5": ["Piano-right_E-5.E-6_0.5"], "65.0": ["Piano-right_E5.E6_1.0", "Piano-left_G#2_1.0"], "66.0": ["Piano-right_C4.E4.F#4_2.0", "Piano-left_A2_2.0"], "68.0": ["Piano-right_F#4.E4.C#4_1.0", "Piano-left_B-2_1.0"], "69.0": ["Piano-right_A3.E-4_3.0", "Piano-right_F#4_1.5", "Piano-left_B1.B2_3.0"], "70.5": ["Piano-right_A4_0.5"], "71.0": ["Piano-right_G4_0.5"], "71.5": ["Piano-right_F#4_0.5"], "72.0": ["Piano-right_G3.E4_1.0", "Piano-left_E3.E2_1.0"], "74.0": ["Piano-right_B3.B4_0.25", "Piano-left_B1.B2_0.25"], "75.0": ["Piano-right_B4.B3_2.0", "Piano-left_B1.B2_2.0"], "77.0": ["Piano-right_E4.E5_0.25", "Piano-left_E2.E3_0.25"], "78.0": ["Piano-right_E5.E4_2.0", "Piano-left_E2.E3_2.0"], "80.0": ["Piano-right_B4.B5_0.25", "Piano-left_B2.B3_0.25"], "81.0": ["Piano-right_B5.B4_2.0", "Piano-left_B2.B3_2.0"], "83.0": ["Piano-right_E6.E5_0.25", "Piano-left_E3.E4_0.25"], "84.0": ["Piano-right_E5.E6_2.0", "Piano-left_E3.E4_2.0"], "86.0": ["Piano-right_F5.B5.D6.F6_0.25", "Piano-left_G3.B3.D4.F4_0.25"], "87.0": ["Piano-right_F5.B5.D6.F6_1.5", "Piano-left_G3.B3.D4.F4_1.5"], "88.5": ["Piano-right_E6_0.25"], "88.75": ["Piano-right_D6_0.25"], "89.0": ["Piano-right_C6_0.25"], "89.25": ["Piano-right_B5_0.25"], "89.5": ["Piano-right_A5_0.25"], "89.75": ["Piano-right_G5_0.25"], "90.0": ["Piano-right_F5_0.25"], "90.25": ["Piano-right_E5_0.25"], "90.5": ["Piano-right_D5_0.25"], "90.75": ["Piano-right_C5_0.25"], "91.0": ["Piano-right_B4_0.25"], "91.25": ["Piano-right_A4_0.25"], "274/3": ["Piano-right_G4_0.25"], "91.5": ["Piano-right_F4_0.25"], "275/3": ["Piano-right_E4_0.25"], "91.75": ["Piano-right_D4_0.25"], "92.0": ["Piano-right_C4_0.25"], "92.25": ["Piano-right_B3_0.25"], "277/3": ["Piano-right_A3_0.25"], "278/3": ["Piano-right_G3_0.25"], "92.75": ["Piano-right_F#3_0.25"], "93.0": ["Piano-right_G3_0.5"], "95.0": ["Piano-right_F4.D4.G3_0.25", "Piano-left_B2.B1_0.25"], "96.0": ["Piano-right_E4.C4.G3_0.5", "Piano-left_C2.C3_0.5"], "98.0": ["Piano-right_D5.G#5.B5.D6_0.25", "Piano-left_E3.G#3.B3.D4_0.25"], "99.0": ["Piano-right_D5.G#5.B5.D6_1.5", "Piano-left_E3.G#3.B3.D4_1.5"], "100.5": ["Piano-right_C6_0.25"], "100.75": ["Piano-right_B5_0.25"], "27.0": ["Piano-left_D4_2.0", "Piano-left_B3_3.0", "Piano-left_G4_5.0"], "33.0": ["Piano-left_D4_2.0"], "36.0": ["Piano-left_G4_2.0"], "39.0": ["Piano-left_E3_2.0"], "42.0": ["Piano-left_C4_2.0"], "45.0": ["Piano-left_C2_3.0"], "51.0": ["Piano-left_B3.G2_3.0", "Piano-left_E3_6.0"], "62.5": ["Piano-left_A2_0.5"], "63.0": ["Piano-left_E3_6.0", "Piano-left_G2_2.0", "Piano-left_B3_3.0"], "107.0": ["Piano-left_G#2.G#1_0.25"], "108.0": ["Piano-left_A1.A2_0.5"], "110.0": ["Piano-left_B-3_1.0"], "111.0": ["Piano-left_B-3_4.0"], "119.0": ["Piano-left_E4_1.0"], "120.0": ["Piano-left_E4_2.0"], "122.0": ["Piano-left_B-3.E4_1.0"], "123.0": ["Piano-left_E4.B-3_2.0"], "125.0": ["Piano-left_B-3.E4_1.0"], "126.0": ["Piano-left_E4.B-3_2.0"], "128.0": ["Piano-left_B-3.C#4.E4.G4_1.0"], "129.0": ["Piano-left_B-3.C#4.E4_5.0", "Piano-left_G4_2.0"], "131.0": ["Piano-left_F#4_1.0"], "132.0": ["Piano-left_F4_2.0"], "134.0": ["Piano-left_F#4.E4.C#4.B-3_1.0"], "135.0": ["Piano-left_F#4.D4.B3_0.25"], "135.5": ["Piano-left_B3.D4.F#4_0.25"], "136.0": ["Piano-left_B3.D4.F#4_0.25"], "136.5": ["Piano-left_B3.D4.F#4_0.25"], "137.0": ["Piano-left_B3.D4.F#4_0.25"], "137.5": ["Piano-left_B3.D4.F#4_0.25"], "138.0": ["Piano-left_B3.F#3.D3_0.25"], "138.5": ["Piano-left_D3.F#3.B3_0.25"], "139.0": ["Piano-left_D3.F#3.B3_0.25"], "139.5": ["Piano-left_D3.F#3.B3_0.25"], "140.0": ["Piano-left_D3.F#3.B3_0.25"], "140.5": ["Piano-left_D3.F#3.B3_0.25"], "141.0": ["Piano-left_A3.F#3.E-3_0.25"], "141.5": ["Piano-left_E-3.F#3.A3_0.25"], "142.0": ["Piano-left_G3.E3_0.25"], "142.5": ["Piano-left_G3.E3_0.25"], "143.0": ["Piano-left_G3.E3_0.25"], "143.5": ["Piano-left_G3.E3_0.25"], "144.0": ["Piano-left_B3.G3.E3_0.25"]}, "beethoven_opus10_2.mid": {"0.0": ["Piano-right_C4_2.0", "Piano-right_G#4_1.5", "Piano-left_G#2.E-3.G#3_2.0"], "1.5": ["Piano-right_B-4_0.25"], "5/3": ["Piano-right_G#4_0.25"], "1.75": ["Piano-right_G4_0.25", "Piano-right_G#4_0.25"], "2.0": ["Piano-right_C5_1.5", "Piano-right_C#4_2.0", "Piano-left_G2.E-3.G3_2.0"], "3.5": ["Piano-right_B-4_0.5"], "4.0": ["Piano-right_C4.G#4_3.0", "Piano-left_G#2.E-3.G#3_3.0"], "7.0": ["Piano-right_A4_1.0"], "8.0": ["Piano-right_E-4_2.0", "Piano-right_B-4_1.0", "Piano-left_G3_2.0", "Piano-left_C#4_1.0"], "9.5": ["Piano-right_C5_0.25"], "29/3": ["Piano-right_B-4_0.25"], "9.75": ["Piano-right_A4_0.25", "Piano-right_B-4_0.25"], "10.0": ["Piano-right_C#5_1.5", "Piano-right_E-4_1.0", "Piano-left_G#3_2.0"], "11.0": ["Piano-right_G#4_1.0", "Piano-left_C4_1.0"], "11.5": ["Piano-right_C5_0.5"], "12.0": ["Piano-right_G4.B-4_3.0", "Piano-left_E-3.E-4_3.0"], "15.0": ["Piano-right_B4_1.0"], "16.0": ["Piano-right_C5_1.75", "Piano-right_E-4_2.0", "Piano-left_G#3_2.0"], "17.75": ["Piano-right_G#4_0.25"], "18.0": ["Piano-right_E-5_1.75", "Piano-right_G#4.E-4_2.0", "Piano-left_C3.C4.G#3_2.0"], "19.75": ["Piano-right_C5_0.25"], "20.0": ["Piano-right_F4.G#4_2.0", "Piano-right_F5_1.75", "Piano-left_C#3.G#3.C#4_2.0"], "21.75": ["Piano-right_C#5_0.25"], "22.25": ["Piano-right_G#4.C#5_11/3"], "67/3": ["Piano-right_F5_5/3"], "22.5": ["Piano-right_G#5_2.0"], "24.5": ["Piano-right_G5_0.5"], "25.0": ["Piano-right_F5_0.5"], "25.5": ["Piano-right_E-5_0.5"], "26.0": ["Piano-right_B-4.C#5_1.0", "Piano-left_G3.E-4_1.0"], "27.0": ["Piano-right_G#4.C5_1.0", "Piano-left_E-4.G#3_1.0"], "28.0": ["Piano-right_E-4_1.0", "Piano-right_E-5_1.5", "Piano-left_C4_1.5", "Piano-left_E-3_2.0"], "29.0": ["Piano-right_E-4_1.0"], "29.5": ["Piano-right_C5_0.5", "Piano-left_G#3_0.5"], "30.0": ["Piano-right_B-4.C5_0.0", "Piano-right_E-4_1.0", "Piano-right_B-4.C5_0.25", "Piano-right_B-4_0.25", "Piano-left_E-3.G3_1.0"], "30.25": ["Piano-right_C5_0.25", "Piano-right_B-4_0.25"], "91/3": ["Piano-right_A4_0.25", "Piano-right_B-4_0.5"], "30.5": ["Piano-right_C#5_0.25"], "30.75": ["Piano-right_C5_0.25"], "31.0": ["Piano-right_E-5_0.25"], "31.25": ["Piano-right_C#5_0.25"], "31.5": ["Piano-right_C5_0.25"], "95/3": ["Piano-right_C#5_0.25"], "31.75": ["Piano-right_B-4_0.25"], "32.0": ["Piano-right_C4_2.0", "Piano-right_G#4_1.5", "Piano-left_G#2_2.0"], "33.5": ["Piano-right_B-4_0.25", "Piano-left_E-3_0.5"], "101/3": ["Piano-right_G#4_0.25"], "33.75": ["Piano-right_G4_0.25", "Piano-right_G#4_0.25"], "34.0": ["Piano-right_C5_1.5", "Piano-right_C#4_2.0", "Piano-left_G2_2.0"], "35.5": ["Piano-right_B-4_0.5", "Piano-left_E-3_0.5"], "36.0": ["Piano-right_C4.G#4_2.0", "Piano-left_G#2_0.5"], "40.0": ["Piano-right_B-4_1.0", "Piano-left_G3_2.0"], "41.5": ["Piano-right_C5_0.25", "Piano-left_E-4_0.5"], "125/3": ["Piano-right_B-4_0.25"], "41.75": ["Piano-right_A4_0.25", "Piano-right_B-4_0.25"], "42.0": ["Piano-right_C#5_1.5", "Piano-right_G#4_2.0", "Piano-left_G#3_2.0"], "43.5": ["Piano-right_C5_0.5", "Piano-left_E-4_0.5"], "44.0": ["Piano-right_G4.B-4_2.0", "Piano-left_E-3_0.5"], "48.0": ["Piano-right_E-4_0.25", "Piano-right_C5_1.75"], "49.75": ["Piano-right_G#4_0.25"], "50.0": ["Piano-right_E-4_0.25", "Piano-right_E-5_1.75"], "51.75": ["Piano-right_C5_0.25"], "52.0": ["Piano-right_F4_0.25", "Piano-right_F5_3.0"], "55.0": ["Piano-right_A4.E-5_0.5", "Piano-left_C4_0.5"], "55.5": ["Piano-right_B-4.C#5_0.5", "Piano-left_C#4_0.5"], "56.0": ["Piano-right_G#4_2.0", "Piano-right_C5_1.0", "Piano-left_E-3_2.0", "Piano-left_E-4_0.5"], "57.0": ["Piano-right_E-5_1.0", "Piano-left_C#4_0.5"], "58.0": ["Piano-right_G4_2.0", "Piano-right_C#5_1.0", "Piano-left_E-3_2.0", "Piano-left_B-3_0.5"], "59.0": ["Piano-right_B-4_1.0", "Piano-left_C#4_0.5"], "60.0": ["Piano-right_C#4_1.0", "Piano-right_B-4_2.0", "Piano-left_G#2_3.0", "Piano-left_G3_2.0"], "61.0": ["Piano-right_C4_0.25"], "61.25": ["Piano-right_C#4_0.25"], "61.5": ["Piano-right_E-4_0.25"], "61.75": ["Piano-right_C#4_0.25"], "9.0": ["Piano-left_B-3_1.0"], "22.0": ["Piano-left_F3.G#3_4.0", "Piano-left_C#4.F4_3.75"], "32.5": ["Piano-left_E-3_0.5"], "33.0": ["Piano-left_E-3_0.5"], "34.5": ["Piano-left_E-3_0.5"], "35.0": ["Piano-left_E-3_0.5"], "36.5": ["Piano-left_E-3_0.5"], "37.0": ["Piano-left_C3_0.5"], "37.5": ["Piano-left_G#3_0.5"], "38.0": ["Piano-left_E-3_0.5"], "38.5": ["Piano-left_C4_0.5"], "39.0": ["Piano-left_G#3_0.5"], "39.5": ["Piano-left_E-4_0.5"], "40.5": ["Piano-left_E-4_0.5"], "41.0": ["Piano-left_E-4_0.5"], "42.5": ["Piano-left_E-4_0.5"], "43.0": ["Piano-left_E-4_0.5"], "44.5": ["Piano-left_E-4_0.5"], "45.0": ["Piano-left_D4_0.5"], "45.5": ["Piano-left_E-4_0.5"], "46.0": ["Piano-left_D4_0.5"], "46.5": ["Piano-left_E-4_0.5"], "47.0": ["Piano-left_F4_0.5"], "47.5": ["Piano-left_C#4_0.5"], "48.5": ["Piano-left_G#3_0.5"], "49.0": ["Piano-left_C4_0.5"], "49.5": ["Piano-left_E-4_1/3"], "50.5": ["Piano-left_C3_0.5"], "51.0": ["Piano-left_E-3_0.5"], "51.5": ["Piano-left_G#3_0.5"], "52.5": ["Piano-left_C#3_3.5", "Piano-left_F3_0.5"], "53.0": ["Piano-left_G3_0.5"], "53.5": ["Piano-left_G#3_0.5"], "54.0": ["Piano-left_A3_0.5"], "54.5": ["Piano-left_B-3_0.5"], "56.5": ["Piano-left_D4_0.5"], "57.5": ["Piano-left_C4_0.5"], "58.5": ["Piano-left_C4_0.5"], "59.5": ["Piano-left_G3_0.5"], "62.0": ["Piano-left_G#3_1.0"], "64.0": ["Piano-left_E-4.F4.C4.A3_2.0"], "67.75": ["Piano-left_A2.F3_0.25"], "68.0": ["Piano-left_B-2.F3_3.0"], "72.0": ["Piano-left_C#4.E-4.B-3.G3_2.0"], "75.75": ["Piano-left_G2.E-3_0.25"], "76.0": ["Piano-left_G#2.E-3_3.0"], "80.0": ["Piano-left_B2_0.25", "Piano-left_B3_1.5"], "81.5": ["Piano-left_B3_0.25", "Piano-left_G#3_0.25"], "245/3": ["Piano-left_E-3_0.25"], "81.75": ["Piano-left_B2_0.25", "Piano-left_G#2_0.25"], "82.0": ["Piano-left_E-2_0.25", "Piano-left_B1_0.5"], "83.75": ["Piano-left_B1.B2_0.25"], "84.0": ["Piano-left_G#3.F3.B-1.B-2_3.0"], "92.0": ["Piano-left_B-3.G#3_1.0"], "93.0": ["Piano-left_B-3.G#3_1.0"], "94.0": ["Piano-left_B-3.G#3_1.0"], "95.0": ["Piano-left_B-3.G#3_1.0"]}, "beethoven_opus10_3.mid": {"1.5": ["Piano-right_C4_0.5", "Piano-left_C3_0.5"], "2.0": ["Piano-right_B3_0.5", "Piano-left_B2_0.5"], "2.5": ["Piano-right_C4_0.5", "Piano-left_C3_0.5"], "3.0": ["Piano-right_F4_0.25", "Piano-left_F3_0.25"], "3.5": ["Piano-right_F4_0.25", "Piano-left_F3_0.25"], "4.0": ["Piano-right_E-4_1.0", "Piano-left_E-3_1.0"], "5.5": ["Piano-right_C4_0.5", "Piano-left_C3_0.5"], "6.0": ["Piano-right_B3_0.5", "Piano-left_B2_0.5"], "6.5": ["Piano-right_C4_0.5", "Piano-left_C3_0.5"], "7.0": ["Piano-right_G#4_0.25", "Piano-left_G#3_0.25"], "7.5": ["Piano-right_G#4_0.25", "Piano-left_G#3_0.25"], "8.0": ["Piano-right_G4_1.0", "Piano-left_G3_1.0"], "9.5": ["Piano-right_C4_0.5"], "10.0": ["Piano-right_B3_0.5"], "10.5": ["Piano-right_C4_0.5"], "11.0": ["Piano-right_C5_0.25"], "11.5": ["Piano-right_C5_0.25"], "12.0": ["Piano-right_C5_0.5", "Piano-left_G#3.C4.F#4_4.0"], "12.5": ["Piano-right_D5_0.25"], "38/3": ["Piano-right_C5_0.25"], "12.75": ["Piano-right_B4_0.25", "Piano-right_C5_0.25"], "13.0": ["Piano-right_E-5_0.5"], "13.5": ["Piano-right_D5_0.5"], "14.0": ["Piano-right_F5_0.5"], "14.5": ["Piano-right_E-5_0.5"], "15.0": ["Piano-right_D5_0.5"], "15.5": ["Piano-right_C5_0.5"], "16.0": ["Piano-right_B4_1.0", "Piano-left_G4.D4.G3_1.0"], "17.5": ["Piano-right_G3_0.5", "Piano-left_G2_0.5"], "18.0": ["Piano-right_F#3_0.5", "Piano-left_F#2_0.5"], "18.5": ["Piano-right_G3_0.5", "Piano-left_G2_0.5"], "19.0": ["Piano-right_C4_0.25", "Piano-left_C3_0.25"], "19.5": ["Piano-right_C4_0.25", "Piano-left_C3_0.25"], "20.0": ["Piano-right_B3_1.0", "Piano-left_B2_1.0"], "21.5": ["Piano-right_G3_0.5", "Piano-left_G2_0.5"], "22.0": ["Piano-right_F#3_0.5", "Piano-left_F#2_0.5"], "22.5": ["Piano-right_G3_0.5", "Piano-left_G2_0.5"], "23.0": ["Piano-right_E-4_0.25", "Piano-left_E-3_0.25"], "23.5": ["Piano-right_E-4_0.25", "Piano-left_E-3_0.25"], "24.0": ["Piano-right_D4_1.0", "Piano-left_D3_1.0"], "25.5": ["Piano-right_G3_0.25", "Piano-left_G2_0.25"], "26.0": ["Piano-right_B3_0.25", "Piano-left_B2_0.25"], "26.5": ["Piano-right_D4_0.25", "Piano-left_D3_0.25"], "27.0": ["Piano-right_F4_0.25", "Piano-left_F3_0.25"], "27.5": ["Piano-right_G#4_0.25", "Piano-left_G#3_0.25"], "28.0": ["Piano-right_B4_0.25", "Piano-left_B3_0.25"], "28.5": ["Piano-right_D5_0.25", "Piano-left_D4_0.25"], "29.0": ["Piano-right_F5_0.25", "Piano-left_F4_0.25"], "29.5": ["Piano-right_G#5_0.25", "Piano-left_G#4_0.25"], "30.0": ["Piano-right_G5_0.25", "Piano-left_G4_0.25"], "30.5": ["Piano-right_F5_0.25", "Piano-left_F4_0.25"], "31.0": ["Piano-right_E-5_0.25", "Piano-left_E-4_0.25"], "31.5": ["Piano-right_D5_0.25", "Piano-left_D4_0.25"], "32.0": ["Piano-right_C5_1.0", "Piano-left_C4_0.25"], "33.5": ["Piano-right_C5_0.5", "Piano-left_E-4.G4_0.25"], "34.0": ["Piano-right_B4_0.5", "Piano-left_C4_0.25"], "34.5": ["Piano-right_C5_0.5", "Piano-left_E4.G4.B-4_0.25"], "35.0": ["Piano-right_C6_0.25", "Piano-left_E4.G4.B-4_0.25"], "35.5": ["Piano-right_C6_0.25", "Piano-left_E4.G4.B-4_0.25"], "36.0": ["Piano-right_C6_1.0", "Piano-left_C4_0.25"], "37.5": ["Piano-right_F6_0.5", "Piano-left_F4.G#4_0.25"], "38.0": ["Piano-right_E-6_0.5", "Piano-left_C4_0.25"], "38.5": ["Piano-right_D6_0.5", "Piano-left_F4.G#4.B4_0.25"], "39.0": ["Piano-right_C6_0.5", "Piano-left_F4.G#4.B4_0.25"], "39.5": ["Piano-right_B5_0.5", "Piano-left_F4.G#4.B4_0.25"], "40.0": ["Piano-right_D6_0.5", "Piano-left_C4_0.25"], "40.5": ["Piano-right_C6_0.5", "Piano-left_E-4.G4_0.25"], "41.5": ["Piano-right_C5_0.5", "Piano-left_E-4.G4_0.25"], "42.0": ["Piano-right_B4_0.5", "Piano-left_C4_0.25"], "42.5": ["Piano-right_C5_0.5", "Piano-left_E4.G4.B-4_0.25"], "43.0": ["Piano-right_C6_0.25", "Piano-left_E4.G4.B-4_0.25"], "43.5": ["Piano-right_C6_0.25", "Piano-left_E4.G4.B-4_0.25"], "44.0": ["Piano-right_C6_1.0", "Piano-left_C4_0.25"], "45.0": ["Piano-right_D6_0.25", "Piano-right_C6_0.25", "Piano-left_F4.G#4_0.25"], "45.25": ["Piano-right_B5_0.25"], "136/3": ["Piano-right_C6_0.25"], "45.5": ["Piano-right_F6_0.5", "Piano-left_F4.G#4_0.25"], "46.0": ["Piano-right_E-6_0.5", "Piano-left_C4_0.25"], "46.5": ["Piano-right_D6_0.5", "Piano-left_F4.G#4.B4_0.25"], "47.0": ["Piano-right_C6_0.5", "Piano-left_F4.G#4.B4_0.25"], "47.5": ["Piano-right_B5_0.5", "Piano-left_F4.G#4.B4_0.25"], "48.0": ["Piano-right_C6_0.25", "Piano-left_C4.E-4.G4.C5_1.0"], "48.25": ["Piano-right_D6_0.25"], "48.5": ["Piano-right_C6_0.25"], "48.75": ["Piano-right_B5_0.25"], "49.0": ["Piano-right_C6_0.25"], "49.25": ["Piano-right_E-6_0.25"], "49.5": ["Piano-right_D6_0.25", "Piano-left_F#4_0.5"], "49.75": ["Piano-right_C6_0.25"], "50.0": ["Piano-right_B5_0.25", "Piano-left_G4_1.0"], "50.25": ["Piano-right_C6_0.25"], "50.5": ["Piano-right_B5_0.25"], "50.75": ["Piano-right_G#5_0.25"], "51.0": ["Piano-right_G5_0.25"], "51.25": ["Piano-right_F5_0.25"], "51.5": ["Piano-right_E-5_0.25", "Piano-left_B3_0.5"], "51.75": ["Piano-right_D5_0.25"], "52.0": ["Piano-right_C5_0.25", "Piano-left_C4_1.0"], "32.5": ["Piano-left_E-4.G4_0.25"], "33.0": ["Piano-left_E-4.G4_0.25"], "36.5": ["Piano-left_F4.G#4_0.25"], "37.0": ["Piano-left_F4.G#4_0.25"], "41.0": ["Piano-left_E-4.G4_0.25"], "44.5": ["Piano-left_F4.G#4_0.25"], "53.5": ["Piano-left_F#3_0.5"], "54.0": ["Piano-left_G3_1.0"], "55.5": ["Piano-left_B2_0.5"], "56.0": ["Piano-left_C3_1.0"], "57.5": ["Piano-left_F#2_0.5"], "58.0": ["Piano-left_G2_1.0"], "59.0": ["Piano-left_C2.C3_0.5"], "60.0": ["Piano-left_G1.G2_0.5"], "61.0": ["Piano-left_C2.C3_0.5"], "62.0": ["Piano-left_G1.G2_0.5"], "63.0": ["Piano-left_C2.C3_0.5"], "64.0": ["Piano-left_G1.B1.D2.G2_2.0"], "68.0": ["Piano-left_E-2.E-3_2.0"], "70.0": ["Piano-left_G#2.G#3_0.25"], "71.0": ["Piano-left_G2.G3_0.25"], "72.0": ["Piano-left_B-2.F2.F3_2.0"], "76.0": ["Piano-left_E-2.E-3_2.0"], "78.0": ["Piano-left_G#1.G#2_0.25"], "79.0": ["Piano-left_A1.A2_0.25"], "80.0": ["Piano-left_B-1.B-2_2.0"], "84.0": ["Piano-left_E-2.E-3_2.0"], "86.0": ["Piano-left_G#2.G#3_0.25"], "87.0": ["Piano-left_G2.G3_0.25"], "87.75": ["Piano-left_G#2.C3.E-3_1.25"]}, "beethoven_opus10_1.mid": {"0.0": ["Piano-right_E-4.G4.C5_1.5", "Piano-left_C4.G3.E-3.C3_1.5"], "1.75": ["Piano-right_G4_0.25"], "2.0": ["Piano-right_E-5_0.75"], "2.75": ["Piano-right_C5_0.25"], "3.0": ["Piano-right_G5_0.75"], "3.75": ["Piano-right_E-5_0.25"], "4.0": ["Piano-right_C6_0.75"], "4.75": ["Piano-right_G5_0.25"], "5.0": ["Piano-right_E-6_0.25"], "6.0": ["Piano-right_E-6_0.25"], "8.0": ["Piano-right_G4.C5_0.5", "Piano-left_C4.E-4_0.5"], "9.0": ["Piano-right_G4.C5_2.0", "Piano-left_E-4.C4_2.0"], "11.0": ["Piano-right_G4.B4_1.0", "Piano-left_D4.F4_1.0"], "12.0": ["Piano-right_G#4.F4.B4_1.5", "Piano-left_F3.B3.G#3.D4.D3_1.5"], "13.75": ["Piano-right_B4_0.25"], "14.0": ["Piano-right_F5_0.75"], "14.75": ["Piano-right_D5_0.25"], "15.0": ["Piano-right_B5_0.75"], "15.75": ["Piano-right_F5_0.25"], "16.0": ["Piano-right_D6_0.75"], "16.75": ["Piano-right_B5_0.25"], "17.0": ["Piano-right_F6_0.25"], "18.0": ["Piano-right_F6_0.25"], "20.0": ["Piano-right_B4.D5_0.5", "Piano-left_D4.G#4.F4_0.5"], "21.0": ["Piano-right_B4.D5_2.0", "Piano-left_G#4.F4.D4_2.0"], "23.0": ["Piano-right_C5_0.75", "Piano-left_G4.E-4_1.0"], "23.75": ["Piano-right_C5_0.25", "Piano-right_E-5_0.25"], "24.0": ["Piano-right_G5_1.5"], "25.5": ["Piano-right_F5_0.5"], "26.0": ["Piano-right_E-5_1.0", "Piano-left_C4.G3.E-3_1.0"], "27.0": ["Piano-right_D5_2.0", "Piano-left_F3.G#3.B3_2.0"], "29.0": ["Piano-right_C5_0.75", "Piano-left_C4.G3.E-3_1.0"], "29.75": ["Piano-right_G4_0.25", "Piano-right_C5_0.25"], "30.0": ["Piano-right_E-5_0.25", "Piano-right_G5_1.5"], "31.5": ["Piano-right_F5_0.5"], "32.0": ["Piano-right_C5.E-5_1.0", "Piano-left_E-4.G4_1.0"], "33.0": ["Piano-right_B4.D5_2.0", "Piano-left_G#4.F4_2.0"], "35.0": ["Piano-right_C5_0.75", "Piano-left_E-4.G4_1.0"], "35.75": ["Piano-right_G4_0.25", "Piano-right_C5_0.25"], "36.0": ["Piano-right_E-5_0.25", "Piano-right_G4.G5_1.5"], "37.5": ["Piano-right_F5.F4_0.5"], "38.0": ["Piano-right_E-5.E-4_2.0", "Piano-left_G3.C4.E-3_1.0"], "40.0": ["Piano-right_D5.D4_0.25"], "41.0": ["Piano-right_C5.C4_2.0", "Piano-left_G3.E-3_1.0"], "43.0": ["Piano-right_B3.B4_0.25"], "44.0": ["Piano-right_G#3.G#4_2.0", "Piano-left_E-3.C3_1.0"], "46.0": ["Piano-right_G3.G4_0.5"], "49.0": ["Piano-right_B3_1/3"], "148/3": ["Piano-right_D4_1/3"], "149/3": ["Piano-right_F4_1/3"], "50.0": ["Piano-right_G#4_1/3", "Piano-left_G#3.F3.D3.B2_1.0"], "151/3": ["Piano-right_G4_1/3"], "152/3": ["Piano-right_F4_1/3"], "51.0": ["Piano-right_E-4_0.25", "Piano-left_G3.E-3.C3_0.25"], "55.0": ["Piano-right_F3_1/3"], "166/3": ["Piano-right_G#3_1/3"], "167/3": ["Piano-right_D4_1/3"], "56.0": ["Piano-right_F4_1/3", "Piano-left_D3.G#2.F2_1.0"], "169/3": ["Piano-right_E-4_1/3"], "170/3": ["Piano-right_D4_1/3"], "57.0": ["Piano-right_C4_0.25", "Piano-left_C3.G2.E-3_0.25"], "61.0": ["Piano-right_G3_1/3"], "184/3": ["Piano-right_B3_1/3"], "185/3": ["Piano-right_D4_1/3"], "62.0": ["Piano-right_F4_1/3", "Piano-left_G2.G1_0.5"], "187/3": ["Piano-right_D4_1/3"], "188/3": ["Piano-right_B3_1/3"], "63.0": ["Piano-right_G3.E-3.C4_1.5", "Piano-left_G2.C2.C3.E-2_1.5"], "64.75": ["Piano-right_C4_0.25"], "65.0": ["Piano-right_G4_0.75"], "65.75": ["Piano-right_E-4_0.25"], "66.0": ["Piano-right_C5_0.75"], "66.75": ["Piano-right_G4_0.25"], "67.0": ["Piano-right_E-5_0.75"], "67.75": ["Piano-right_C5_0.25"], "68.0": ["Piano-right_G5.G4_0.25", "Piano-left_C3.G3.E-3_0.25"], "69.0": ["Piano-right_G5.G4_0.25", "Piano-left_B2.D3.G3_0.25"], "70.75": ["Piano-right_B3_0.25"], "71.0": ["Piano-right_G4_0.75"], "71.75": ["Piano-right_D4_0.25"], "72.0": ["Piano-right_B4_0.75"], "72.75": ["Piano-right_G4_0.25"], "73.0": ["Piano-right_D5_0.75"], "73.75": ["Piano-right_B4_0.25"], "74.0": ["Piano-right_G5.G4_0.25", "Piano-left_G3.B2.D3_0.25"], "75.0": ["Piano-right_G5.G4_0.25", "Piano-left_G3.C3.E-3_0.25"], "76.75": ["Piano-right_E-4_0.25"], "77.0": ["Piano-right_G4_0.75"], "77.75": ["Piano-right_E-4_0.25"], "78.0": ["Piano-right_C5_0.75"], "78.75": ["Piano-right_G4_0.25"], "79.0": ["Piano-right_E-5_0.75"], "79.75": ["Piano-right_C5_0.25"], "80.0": ["Piano-right_G5_0.75", "Piano-left_E-3.C4.G3_0.25"], "80.75": ["Piano-right_E-5_0.25"], "39.0": ["Piano-left_B3.F3.G#3_2.0"], "42.0": ["Piano-left_D3.F3_2.0"], "45.0": ["Piano-left_D3.B2_1.0"], "81.0": ["Piano-left_G#3.D4.F3_0.25"], "84.0": ["Piano-left_D4.B3.G3_0.25"], "87.0": ["Piano-left_G3.C3.C4.E-3_0.25"], "93.0": ["Piano-left_E-4_9.0"], "96.0": ["Piano-left_C#4_3.0"], "99.0": ["Piano-left_C4_3.0"], "102.0": ["Piano-left_C#4.B-3_3.0"], "105.0": ["Piano-left_G#3.E-4_3.0"], "108.0": ["Piano-left_B-4_3.0", "Piano-left_C5_6.0"], "111.0": ["Piano-left_G#4_3.0"], "114.0": ["Piano-left_G4.B-4_3.0"], "117.0": ["Piano-left_F4.G#4_3.0"], "120.0": ["Piano-left_F#4_3.0", "Piano-left_G#4_6.0"], "123.0": ["Piano-left_F4_3.0"], "126.0": ["Piano-left_E-4.F#4_3.0"], "129.0": ["Piano-left_C#4.F4_3.0"], "132.0": ["Piano-left_B3.E-4_3.0"], "135.0": ["Piano-left_B-3_3.0"], "138.0": ["Piano-left_A3_3.0"], "141.0": ["Piano-left_B-2_6.0"], "142.0": ["Piano-left_F3_1.0"], "143.0": ["Piano-left_G3_1.0"], "144.0": ["Piano-left_G#3_1.0"], "145.0": ["Piano-left_E3_1.0"], "146.0": ["Piano-left_F3_1.0"], "147.0": ["Piano-left_B-2_6.0", "Piano-left_G3_1.0"], "148.0": ["Piano-left_D3_1.0"], "149.0": ["Piano-left_E-3_1.0"], "150.0": ["Piano-left_F3_1.0"], "151.0": ["Piano-left_C3_1.0"], "152.0": ["Piano-left_D3_1.0"], "153.0": ["Piano-left_B-2_6.0", "Piano-left_E-3_1.0"], "154.0": ["Piano-left_F3_1.0"], "155.0": ["Piano-left_G3_1.0"], "156.0": ["Piano-left_G#3_1.0"], "157.0": ["Piano-left_E3_1.0"], "158.0": ["Piano-left_F3_1.0"], "159.0": ["Piano-left_G3_1.0", "Piano-left_B-2_6.0"], "160.0": ["Piano-left_D3_1.0"], "161.0": ["Piano-left_E-3_1.0"], "162.0": ["Piano-left_F3_1.0"], "163.0": ["Piano-left_C3_1.0"], "164.0": ["Piano-left_D3_1.0"], "165.0": ["Piano-left_E-3_0.5"], "165.5": ["Piano-left_B-3_0.5"], "166.0": ["Piano-left_G3_0.5"], "166.5": ["Piano-left_B-3_0.5"], "167.0": ["Piano-left_F3_0.5"], "167.5": ["Piano-left_B-3_0.5"], "168.0": ["Piano-left_E-3_0.5"], "168.5": ["Piano-left_B-3_0.5"], "169.0": ["Piano-left_F3_0.5"], "169.5": ["Piano-left_B-3_0.5"], "170.0": ["Piano-left_G3_0.5"], "170.5": ["Piano-left_B-3_0.5"], "171.0": ["Piano-left_F3_0.5"], "171.5": ["Piano-left_B-3_0.5"], "172.0": ["Piano-left_G3_0.5"], "172.5": ["Piano-left_B-3_0.5"], "173.0": ["Piano-left_G#3_0.5"], "173.5": ["Piano-left_B-3_0.5"], "174.0": ["Piano-left_F3_0.5"], "174.5": ["Piano-left_B-3_0.5"], "175.0": ["Piano-left_G3_0.5"]}, "beethoven_les_adieux_3.mid": {"0.0": ["Piano-right_F6.D6.G#5.G#6_0.25", "Piano-left_F4.G#4.D4.B-3_0.25"], "0.5": ["Piano-right_B-3_0.25", "Piano-left_B-2_0.25"], "0.75": ["Piano-right_A3_0.25", "Piano-left_D3_0.25"], "1.0": ["Piano-right_B-3_0.25", "Piano-left_B-2_0.25"], "1.25": ["Piano-right_D4_0.25", "Piano-left_D3_0.25"], "1.5": ["Piano-right_F4_0.25", "Piano-left_D3_0.25"], "1.75": ["Piano-right_D4_0.25", "Piano-left_F3_0.25"], "2.0": ["Piano-right_F4_0.25", "Piano-left_D3_0.25"], "2.25": ["Piano-right_G#4_0.25", "Piano-left_F3_0.25"], "2.5": ["Piano-right_F4_0.25", "Piano-left_D3_0.25"], "2.75": ["Piano-right_D4_0.25", "Piano-left_F3_0.25"], "3.0": ["Piano-right_G#4_0.25", "Piano-left_F3_0.25"], "3.25": ["Piano-right_F4_0.25", "Piano-left_G#3_0.25"], "3.5": ["Piano-right_G#4_0.25", "Piano-left_F3_0.25"], "3.75": ["Piano-right_B-4_0.25", "Piano-left_G#3_0.25"], "4.0": ["Piano-right_G#4_0.25", "Piano-left_F3_0.25"], "4.25": ["Piano-right_F4_0.25", "Piano-left_G#3_0.25"], "4.5": ["Piano-right_B-4_0.25", "Piano-left_B-3_0.25"], "4.75": ["Piano-right_G#4_0.25", "Piano-left_D4_0.25"], "5.0": ["Piano-right_B-4_0.25", "Piano-left_B-3_0.25"], "5.25": ["Piano-right_D5_0.25", "Piano-left_D4_0.25"], "5.5": ["Piano-right_B-4_0.25", "Piano-left_B-3_0.25"], "5.75": ["Piano-right_G#4_0.25", "Piano-left_D4_0.25"], "6.0": ["Piano-right_F5_0.25", "Piano-left_D4_0.25"], "6.25": ["Piano-right_D5_0.25", "Piano-left_F4_0.25"], "6.5": ["Piano-right_F5_0.25", "Piano-left_D4_0.25"], "6.75": ["Piano-right_G#5_0.25", "Piano-left_F4_0.25"], "7.0": ["Piano-right_F5_0.25", "Piano-left_D4_0.25"], "7.25": ["Piano-right_D5_0.25", "Piano-left_F4_0.25"], "7.5": ["Piano-right_G#5_0.25", "Piano-left_F4_0.25"], "7.75": ["Piano-right_F5_0.25", "Piano-left_G#4_0.25"], "8.0": ["Piano-right_G#5_0.25", "Piano-left_F4_0.25"], "8.25": ["Piano-right_B-5_0.25", "Piano-left_G#4_0.25"], "8.5": ["Piano-right_G#5_0.25", "Piano-left_F4_0.25"], "8.75": ["Piano-right_F5_0.25", "Piano-left_G#4_0.25"], "9.0": ["Piano-right_B-5_0.25", "Piano-left_D5_0.25"], "9.25": ["Piano-right_G#5_0.25", "Piano-left_F5_0.25"], "9.5": ["Piano-right_B-5_0.25", "Piano-left_D5_0.25"], "9.75": ["Piano-right_D6_0.25", "Piano-left_F5_0.25"], "10.0": ["Piano-right_B-5_0.25", "Piano-left_D5_0.25"], "10.25": ["Piano-right_G#5_0.25", "Piano-left_F5_0.25"], "10.5": ["Piano-right_D6_0.25", "Piano-left_F5_0.25"], "10.75": ["Piano-right_B-5_0.25", "Piano-left_G#5_0.25"], "11.0": ["Piano-right_D6_0.25", "Piano-left_F5_0.25"], "11.25": ["Piano-right_F6_0.25", "Piano-left_G#5_0.25"], "11.5": ["Piano-right_D6_0.25", "Piano-left_F5_0.25"], "11.75": ["Piano-right_B-5_0.25", "Piano-left_G#5_0.25"], "12.0": ["Piano-right_F6_0.25"], "12.25": ["Piano-right_D6_0.25"], "12.5": ["Piano-right_F6_0.25"], "12.75": ["Piano-right_G#6_0.25"], "13.0": ["Piano-right_F6_0.25", "Piano-left_F5_1.5", "Piano-left_G#5_0.5"], "13.25": ["Piano-right_D6_0.25"], "13.5": ["Piano-right_B-5_0.25", "Piano-left_D5_1.0"], "13.75": ["Piano-right_A5_0.25"], "14.0": ["Piano-right_B-5_0.25"], "14.25": ["Piano-right_D6_0.25"], "14.5": ["Piano-right_F6_0.25"], "14.75": ["Piano-right_D6_0.25"], "15.0": ["Piano-right_F6_0.25"], "15.25": ["Piano-right_D6_0.25"], "15.5": ["Piano-right_F6_0.25"], "15.75": ["Piano-right_G#6_0.25"], "16.0": ["Piano-right_F6_0.25", "Piano-left_G#5_0.5", "Piano-left_F5_1.5"], "16.25": ["Piano-right_D6_0.25"], "16.5": ["Piano-right_B-5_0.25", "Piano-left_D5_1.0"], "16.75": ["Piano-right_A5_0.25"], "17.0": ["Piano-right_B-5_0.25"], "17.25": ["Piano-right_D6_0.25"], "17.5": ["Piano-right_F6_0.25"], "17.75": ["Piano-right_D6_0.25"], "18.0": ["Piano-right_F5_0.25"], "18.25": ["Piano-right_D5_0.25"], "18.5": ["Piano-right_F5_0.25"], "18.75": ["Piano-right_G#5_0.25"], "19.0": ["Piano-right_F5_0.25", "Piano-left_G#4_0.5", "Piano-left_F4_1.5"], "19.25": ["Piano-right_D5_0.25"], "19.5": ["Piano-right_B-4_0.25", "Piano-left_D4_1.0"], "19.75": ["Piano-right_A4_0.25"], "20.0": ["Piano-right_B-4_0.25"], "20.25": ["Piano-right_D5_0.25"], "20.5": ["Piano-right_F5_0.25"], "20.75": ["Piano-right_D5_0.25"], "21.0": ["Piano-right_F5_0.25"], "21.25": ["Piano-right_D5_0.25"], "21.5": ["Piano-right_F5_0.25"], "21.75": ["Piano-right_G#5_0.25"], "22.0": ["Piano-right_F5_0.25", "Piano-left_F4_1.5", "Piano-left_G#4_0.5"], "22.25": ["Piano-right_D5_0.25"], "22.5": ["Piano-right_B-4_0.25", "Piano-left_D4_1.0"], "22.75": ["Piano-right_A4_0.25"], "23.0": ["Piano-right_B-4_0.25"], "23.25": ["Piano-right_D5_0.25"], "23.5": ["Piano-right_F5_0.25"], "23.75": ["Piano-right_D5_0.25"], "24.0": ["Piano-right_G#5.D5.F5.G#4_0.25", "Piano-left_B-3.D3.B-2.F3_0.25"], "24.5": ["Piano-right_B-3_0.25", "Piano-left_B-2_0.25"], "24.75": ["Piano-right_A3_0.25"], "25.0": ["Piano-right_B-3_0.25", "Piano-left_B-2_0.25"], "25.25": ["Piano-right_A3_0.25"], "25.5": ["Piano-left_D3_0.25"], "26.0": ["Piano-left_F3_0.25"], "26.5": ["Piano-left_B-3_0.25"], "27.0": ["Piano-left_D4_0.25"], "27.5": ["Piano-left_F4_0.25"], "28.0": ["Piano-left_G#4.B-4_0.25"], "28.5": ["Piano-left_B-4.G#4_0.25"], "29.0": ["Piano-left_G#4.B-4_0.25"], "29.5": ["Piano-left_B-4.G#4_0.25"], "30.0": ["Piano-left_E-4.G4.B-4_1.0"], "31.5": ["Piano-left_F4.G#4.B-3.B-4_1.0"], "33.0": ["Piano-left_E-4.B-4.G4_1.0"], "35.5": ["Piano-left_E4.G4.B-4.C5_1/3"], "36.0": ["Piano-left_G#4.F4.C5_1.0"], "37.5": ["Piano-left_C5.B-4.C4.G4_1.0"], "39.0": ["Piano-left_F4.G#4.C5_1.0"], "41.5": ["Piano-left_F4.D4.G#4.B-4_1/3"], "42.0": ["Piano-left_G4.B-4.E-4_1.0"], "43.5": ["Piano-left_G#3.C4.F4_1.0"], "45.0": ["Piano-left_E-4.B-3.G4_1.0"], "46.5": ["Piano-left_B-3.F4.D4_1.0"], "47.5": ["Piano-left_B-3_1/3"], "48.0": ["Piano-left_B-3_0.5"], "48.5": ["Piano-left_G3_0.5"], "49.0": ["Piano-left_E-3_0.5"], "49.5": ["Piano-left_D3_0.5"], "50.0": ["Piano-left_F3_0.5"], "50.5": ["Piano-left_B-3_1/3"], "51.0": ["Piano-left_B-3_0.5"], "51.5": ["Piano-left_G3_0.5"], "52.0": ["Piano-left_E-3_1/3"], "52.5": ["Piano-left_E-3_0.5"], "53.0": ["Piano-left_G3_0.5"], "53.5": ["Piano-left_E3.C4_1/3"], "54.0": ["Piano-left_C4.F3_0.5"], "54.5": ["Piano-left_G#3_0.5"], "55.0": ["Piano-left_F3_0.5"], "55.5": ["Piano-left_E3_0.5"]}, "beethoven_les_adieux_2.mid": {"0.0": ["Piano-right_G4_0.75", "Piano-left_C3.E-4_4.0"], "0.75": ["Piano-right_F#4_0.25"], "1.0": ["Piano-right_A4_3.0", "Piano-left_F#3_1.0"], "4.0": ["Piano-right_G4_0.75", "Piano-left_C3.E-4_4.0"], "4.75": ["Piano-right_F#4_0.25"], "5.0": ["Piano-right_A4_2.75", "Piano-left_F#3_1.0"], "7.0": ["Piano-right_A4_1.0", "Piano-left_F#3_1.0"], "7.75": ["Piano-right_E-5_0.25"], "8.0": ["Piano-right_E-5_1.0"], "9.0": ["Piano-right_D4_1.0", "Piano-right_D5_0.75", "Piano-left_B2.G3_1.0"], "9.75": ["Piano-right_G4_0.25"], "10.0": ["Piano-right_G4_1.0"], "11.0": ["Piano-right_C4_1.0", "Piano-right_F#4_0.75", "Piano-left_D3.A3_1.0"], "11.75": ["Piano-right_A4_0.25"], "12.0": ["Piano-right_A4_0.75"], "12.75": ["Piano-right_B4_2.0"], "13.0": ["Piano-right_B3.D4_1.0", "Piano-left_G2.G3_1.0"], "14.0": ["Piano-right_B3.D4_1.0", "Piano-left_G2.G3_1.0"], "14.5": ["Piano-right_C5_0.25"], "44/3": ["Piano-right_B4_1/3"], "14.75": ["Piano-right_A4_0.25"], "15.0": ["Piano-right_B4_0.5"], "15.5": ["Piano-right_C5_0.5"], "16.0": ["Piano-right_E-5_0.75", "Piano-left_F3.G#4_4.0"], "16.75": ["Piano-right_D5_0.25"], "17.0": ["Piano-right_F5_2.75", "Piano-left_B3_1.0"], "19.75": ["Piano-right_D5_0.25", "Piano-right_F5_0.25"], "20.0": ["Piano-right_E-5_0.75", "Piano-left_F3.G#4_4.0"], "20.75": ["Piano-right_D5_0.25"], "21.0": ["Piano-right_F5_3.0", "Piano-left_B3_1.0"], "23.0": ["Piano-right_D5_0.75", "Piano-left_B3_1.0"], "23.75": ["Piano-right_G#5_0.25"], "24.0": ["Piano-right_G#5_1.0"], "25.0": ["Piano-right_G4_1.0", "Piano-right_G5_0.75", "Piano-left_E-3.C4_1.0"], "25.75": ["Piano-right_C5_0.25"], "26.0": ["Piano-right_C5_1.0"], "27.0": ["Piano-right_F4_1.0", "Piano-right_B4_0.75", "Piano-left_G3.D4_1.0"], "27.75": ["Piano-right_D5_0.25"], "28.0": ["Piano-right_D5_0.75"], "28.75": ["Piano-right_E-5_2.25"], "29.0": ["Piano-right_E-4_1.0", "Piano-left_C3.C4_1.0"], "30.0": ["Piano-right_E-4_0.5", "Piano-left_C3.C4_0.5"], "30.5": ["Piano-right_G#4_0.5", "Piano-left_E-4.C4_0.5"], "31.0": ["Piano-right_G4_0.5", "Piano-left_B-3.C#4.E-4_0.5"], "31.5": ["Piano-right_G#4_0.5", "Piano-left_E-4.C4.G#3_0.5"], "32.0": ["Piano-right_C5_0.5", "Piano-left_G3.B-3.E-4_1.0"], "32.5": ["Piano-right_B-4_0.25"], "98/3": ["Piano-right_C5_0.25"], "32.75": ["Piano-right_B-4_0.25", "Piano-right_A4_0.25"], "33.0": ["Piano-right_B-4_0.75", "Piano-left_G3.B-3.E4_1.5"], "33.75": ["Piano-right_C5_0.25"], "34.0": ["Piano-right_C#5_1.25"], "35.25": ["Piano-right_C5_0.25"], "35.5": ["Piano-right_B-5_0.25", "Piano-left_E3.G3.C4_0.5"], "35.75": ["Piano-right_G5_0.25"], "36.0": ["Piano-right_G5_1.5", "Piano-left_E3.G3.C4_1.0"], "37.5": ["Piano-right_B-5_0.25"], "37.75": ["Piano-right_G#5_0.25"], "39.0": ["Piano-right_G#4_0.5"], "39.5": ["Piano-right_G4_0.5"], "40.0": ["Piano-right_A3.C4_3.0", "Piano-right_G4_0.75", "Piano-left_D2_3.0", "Piano-left_E-3_1.0"], "40.75": ["Piano-right_F#4_0.25"], "41.0": ["Piano-right_A4_2.0", "Piano-left_F#2_1.0"], "43.0": ["Piano-right_D4_1.0", "Piano-right_A4_0.75", "Piano-left_B-2.D3.B-3_1.0"], "43.75": ["Piano-right_G4_0.25"], "44.0": ["Piano-right_C4.D4_1.0", "Piano-right_G4_0.75", "Piano-left_A2.D3.A3_1.0"], "44.75": ["Piano-right_F#4_0.25"], "45.0": ["Piano-right_B-3.D4_1.0", "Piano-right_A4_0.75", "Piano-left_G2.D3.G3_1.0"], "45.75": ["Piano-right_G4_0.25"], "46.0": ["Piano-right_A3.D4_1.0", "Piano-right_B-4_0.75", "Piano-left_F#2.D3.F#3_1.0"], "46.75": ["Piano-right_A4_0.25"], "47.0": ["Piano-right_F#4_0.25"], "47.25": ["Piano-right_A4_0.25"], "47.5": ["Piano-right_C5_0.25"], "47.75": ["Piano-right_E-5_0.25"], "48.0": ["Piano-right_D5_0.25"], "48.25": ["Piano-right_C5_0.25"], "48.5": ["Piano-right_B-4_0.25"], "48.75": ["Piano-right_A4_0.25"], "49.0": ["Piano-right_C5_0.25"], "49.25": ["Piano-right_F#5_0.25"], "49.5": ["Piano-right_A5_0.25"], "49.75": ["Piano-right_C6_0.25"], "50.0": ["Piano-right_B-5_0.25"], "50.25": ["Piano-right_A5_0.25"], "50.5": ["Piano-right_G5_0.25"], "50.75": ["Piano-right_F#5_0.25"], "51.0": ["Piano-right_A5_0.25"], "51.25": ["Piano-right_C6_0.25"], "2.0": ["Piano-left_A3_1.0"], "3.0": ["Piano-left_F#3_1.0"], "6.0": ["Piano-left_A3_1.0"], "18.0": ["Piano-left_D4_1.0"], "19.0": ["Piano-left_B3_1.0"], "22.0": ["Piano-left_D4_1.0"], "34.5": ["Piano-left_F3.G#3.C#4_0.5"], "35.0": ["Piano-left_E3.G3.C4_0.5"], "37.0": ["Piano-left_F3.G#3.C4_1.0"], "42.0": ["Piano-left_A2_1.0"], "56.0": ["Piano-left_F#3.A3_0.25"], "56.25": ["Piano-left_D4_0.25"], "56.5": ["Piano-left_F#3.A3_0.25"], "56.75": ["Piano-left_D4_0.25"], "57.0": ["Piano-left_F#3.A3_0.25"], "57.25": ["Piano-left_D4_0.25"], "57.5": ["Piano-left_F#3.A3_0.25"], "57.75": ["Piano-left_D4_0.25"], "58.0": ["Piano-left_F#3.A3_0.25"], "58.25": ["Piano-left_D4_0.25"], "58.5": ["Piano-left_F#3.A3_0.25"], "58.75": ["Piano-left_D4_0.25"], "59.0": ["Piano-left_G3.B3_0.25"], "59.25": ["Piano-left_D4_0.25"], "59.5": ["Piano-left_G3.B3_0.25"], "59.75": ["Piano-left_D4_0.25"], "60.0": ["Piano-left_A3.C4_0.25"], "60.25": ["Piano-left_D4_0.25"], "60.5": ["Piano-left_A3.C4_0.25"], "60.75": ["Piano-left_D4_0.25"], "61.0": ["Piano-left_A3.C4_0.25"], "61.25": ["Piano-left_D4_0.25"], "61.5": ["Piano-left_A3.C4_0.25"], "61.75": ["Piano-left_D4_0.25"], "62.0": ["Piano-left_A3.C4_0.25"], "62.25": ["Piano-left_D4_0.25"], "62.5": ["Piano-left_G3.B3_0.25"], "62.75": ["Piano-left_D4_0.25"], "63.0": ["Piano-left_F#3.A3_0.25"], "63.25": ["Piano-left_D4_0.25"], "63.5": ["Piano-left_F#3.A3_0.25"], "63.75": ["Piano-left_D4_0.25"], "64.0": ["Piano-left_F#3.A3_0.25"], "64.25": ["Piano-left_D4_0.25"], "64.5": ["Piano-left_F#3.A3_0.25"], "64.75": ["Piano-left_D4_0.25"], "65.0": ["Piano-left_F#3.A3_0.25"], "65.25": ["Piano-left_D4_0.25"], "65.5": ["Piano-left_F#3.A3_0.25"], "65.75": ["Piano-left_D4_0.25"], "66.0": ["Piano-left_F#3.A3_0.25"], "66.25": ["Piano-left_D4_0.25"], "66.5": ["Piano-left_F#3.A3_0.25"], "66.75": ["Piano-left_D4_0.25"], "67.0": ["Piano-left_G3.B3_0.25"], "67.25": ["Piano-left_D4_0.25"], "67.5": ["Piano-left_G3.B3_0.25"], "67.75": ["Piano-left_D4_0.25"], "68.0": ["Piano-left_A3.C4_0.25"], "68.25": ["Piano-left_D4_0.25"], "68.5": ["Piano-left_A3.C4_0.25"], "68.75": ["Piano-left_D4_0.25"], "69.0": ["Piano-left_A3.C4_0.25"], "69.25": ["Piano-left_D4_0.25"], "69.5": ["Piano-left_A3.C4_0.25"], "69.75": ["Piano-left_D4_0.25"], "70.0": ["Piano-left_A3.C4_0.25"], "70.25": ["Piano-left_D4_0.25"]}, "beethoven_les_adieux_1.mid": {"0.0": ["Piano-right_G4.E-4_1.0"], "1.0": ["Piano-right_F4.B-3_1.0"], "2.0": ["Piano-right_G3.E-4_1.5", "Piano-left_C2.C3_1.5"], "3.5": ["Piano-right_E-4_1/3", "Piano-left_C3.E-3_0.5"], "3.75": ["Piano-right_G#4_0.25"], "4.0": ["Piano-right_G4_0.5", "Piano-left_B-2.E3_0.5"], "4.5": ["Piano-right_G4_1/3", "Piano-left_B-2.E3_0.5"], "4.75": ["Piano-right_C#5_0.25"], "5.0": ["Piano-right_C5_0.5", "Piano-left_A2.F3_0.5"], "5.5": ["Piano-right_C5_0.25", "Piano-left_F#3.G#2_0.5"], "17/3": ["Piano-right_D5.C5_0.0", "Piano-right_B4_0.25"], "5.75": ["Piano-right_C5_0.25", "Piano-right_D5_0.25"], "6.0": ["Piano-right_E-5_0.75", "Piano-right_E-4_0.5", "Piano-left_G3_0.5", "Piano-left_G2_1.5"], "6.5": ["Piano-right_F#4.E-4_0.5", "Piano-left_A3_0.5"], "6.75": ["Piano-right_C5_0.25"], "7.0": ["Piano-right_B4.D4.G4_0.5", "Piano-left_B3_0.5"], "7.5": ["Piano-right_G5_0.25"], "7.75": ["Piano-right_E-6_0.25"], "8.0": ["Piano-right_E-6_0.75", "Piano-right_E-5_0.5", "Piano-left_G4_0.5", "Piano-left_G3_1.5"], "8.5": ["Piano-right_F#5.E-5_0.5", "Piano-left_A4_0.5"], "8.75": ["Piano-right_C6_0.25"], "9.0": ["Piano-right_D5.G5.B5_0.5", "Piano-left_B4_0.5"], "9.5": ["Piano-right_B-5.D5.G5_0.5", "Piano-left_B-4.G4_0.5"], "10.0": ["Piano-right_B-5_1.25", "Piano-right_D5_0.5", "Piano-left_G#4.F4_0.5", "Piano-left_B-4_1.5"], "10.5": ["Piano-right_E-5_0.5", "Piano-left_E-4.G4_0.5"], "11.0": ["Piano-right_F5_0.25", "Piano-left_D4.F4_0.5"], "11.25": ["Piano-right_B-4_0.25"], "34/3": ["Piano-right_C5_0.25"], "11.5": ["Piano-right_A4_0.25", "Piano-left_D4.B-3_0.5"], "35/3": ["Piano-right_B-4_0.25"], "11.75": ["Piano-right_G#4_0.25"], "12.0": ["Piano-right_B-3.E4.G4.C#4_1.0"], "13.0": ["Piano-right_D4.F4.G#3_1.0", "Piano-left_B-2.B-1_1.0"], "14.0": ["Piano-right_F#3.E-4_1.5", "Piano-left_B1.B2_1.5"], "15.5": ["Piano-right_F#4_1/3", "Piano-right_E-4_0.5", "Piano-left_B2.F#3_0.5"], "15.75": ["Piano-right_B4_0.25"], "16.0": ["Piano-right_B4.E4_0.5", "Piano-left_F#3.C#3_0.5"], "16.5": ["Piano-right_E4_0.5", "Piano-right_B-4_1/3", "Piano-left_F#3.C#3_0.5"], "16.75": ["Piano-right_E5_0.25"], "17.0": ["Piano-right_E-5.E-4_0.5", "Piano-left_B2.F#3_0.5"], "17.5": ["Piano-right_E-5_0.25", "Piano-left_B-2_0.5", "Piano-left_F#3_1.0"], "53/3": ["Piano-right_F5.E-5_0.0", "Piano-right_D5_0.25"], "17.75": ["Piano-right_E-5_0.25", "Piano-right_F5_0.25"], "18.0": ["Piano-right_F#5_0.75", "Piano-right_C5_0.5", "Piano-left_A2_1.0"], "18.5": ["Piano-right_C5_0.5", "Piano-left_F3_0.5"], "18.75": ["Piano-right_E-5_0.25"], "19.0": ["Piano-right_D5.B-4_0.5", "Piano-left_F3.B-2_0.5"], "19.5": ["Piano-right_B-4_1.0", "Piano-right_C#5_0.25", "Piano-left_G#2_0.5", "Piano-left_E3_1.0"], "59/3": ["Piano-right_E-5.C#5_0.0", "Piano-right_C5_0.25"], "19.75": ["Piano-right_C#5_0.25", "Piano-right_E-5_0.25"], "20.0": ["Piano-right_E5_0.75", "Piano-left_G2_1.0"], "20.5": ["Piano-right_B-4_0.5", "Piano-left_E-3_0.5"], "20.75": ["Piano-right_E-5_0.25", "Piano-right_C#5_0.25"], "21.0": ["Piano-right_B4.G#4_0.5", "Piano-left_E-3.G#2_0.5"], "21.5": ["Piano-right_E-4.E-5.B-4_0.5", "Piano-left_F#3.F#2.B-2_0.5"], "22.0": ["Piano-right_D5.G#4.D4.B-4_0.5", "Piano-left_F2.B-2.F3_0.5"], "23.25": ["Piano-right_D4.B-4.D5.G#4_0.25", "Piano-left_B-2.F3.F2_0.25"], "23.5": ["Piano-right_B-4.E-4.F#4.E-5_0.25", "Piano-left_E-2.B-2.E-3_0.25"], "23.75": ["Piano-right_F#4.E-5.B-4.E-4_0.25", "Piano-left_B-2.E-2.E-3_0.25"], "24.0": ["Piano-right_F5.F4.B-4_0.5", "Piano-left_B-2.D3.D2_0.5"], "25.25": ["Piano-right_D5.B-4_0.25", "Piano-left_F4.G#4_0.25"], "25.5": ["Piano-right_B-4.E-5_0.25", "Piano-left_F#4.E-4_0.25"], "25.75": ["Piano-right_E-5.B-4_0.25", "Piano-left_F#4.E-4_0.25"], "26.0": ["Piano-right_F5.B-4_0.5", "Piano-left_D4.F4_0.5"], "27.25": ["Piano-right_B-4.F5_0.25", "Piano-left_F4.D4_0.25"], "27.5": ["Piano-right_G5.B-4_0.25", "Piano-left_E-4.C#4_0.25"], "27.75": ["Piano-right_G#4.G#5_0.25", "Piano-left_B3.E-4_0.25"], "28.0": ["Piano-right_G#4.G#5_0.5", "Piano-left_B3.E-4_0.5"], "29.25": ["Piano-right_F5.B-4_0.25", "Piano-left_D4.F4_0.25"], "29.5": ["Piano-right_G5.B-4_0.25", "Piano-left_C#4.E-4_0.25"], "29.75": ["Piano-right_G#5.G#4_0.25", "Piano-left_C4.E-4_0.25"], "30.5": ["Piano-right_G#5.G#4_0.5", "Piano-left_C4.E-4_0.5"], "31.5": ["Piano-right_G#4.G#5_0.5", "Piano-left_E-4.C4_0.5"], "32.0": ["Piano-right_G#5.G#4_1.5", "Piano-left_E-4.C4_1.5"], "33.5": ["Piano-right_G4_0.5", "Piano-right_D5_0.25", "Piano-left_D4.B3_0.25"], "33.75": ["Piano-right_G5_0.25", "Piano-left_C#4.B-3_0.25"], "34.0": ["Piano-right_G4.G5_0.5", "Piano-left_B-3.C#4_0.5"], "34.5": ["Piano-right_C5_0.25", "Piano-right_F4_0.5", "Piano-left_A3.C4_0.25"], "34.75": ["Piano-right_F5_0.25", "Piano-left_G#3.B3_0.25"], "35.0": ["Piano-right_F4.F5_0.5", "Piano-left_G#3.B3_0.5"], "35.5": ["Piano-right_B-4_0.25", "Piano-right_E-4_0.5", "Piano-left_B-3.G3_0.25"], "35.75": ["Piano-right_E-5_0.25", "Piano-left_F#3.A3_0.25"], "36.0": ["Piano-right_G#4.B-4_1.5", "Piano-left_G#3.F3_1.5"], "37.5": ["Piano-left_G3.E-3_0.5"], "38.0": ["Piano-left_D3.F3_0.5"], "38.5": ["Piano-left_C3.E-3_0.5"], "39.0": ["Piano-left_B-2.D3_0.5"], "39.5": ["Piano-left_F3.B-2.D3_0.5"], "40.0": ["Piano-left_E-2_0.25"], "40.25": ["Piano-left_B-2_0.25"], "40.5": ["Piano-left_G3_0.25"], "40.75": ["Piano-left_B-2_0.25"], "41.0": ["Piano-left_E-2_0.25"], "41.25": ["Piano-left_B-2_0.25"], "41.5": ["Piano-left_G3_0.25"], "41.75": ["Piano-left_B-2_0.25"], "42.0": ["Piano-left_F2_0.25"], "42.25": ["Piano-left_B-2_0.25"], "42.5": ["Piano-left_G#3_0.25"], "42.75": ["Piano-left_B-2_0.25"], "43.0": ["Piano-left_F2_0.25"], "43.25": ["Piano-left_B-2_0.25"], "43.5": ["Piano-left_G#3_0.25"], "43.75": ["Piano-left_B-2_0.25"], "44.0": ["Piano-left_G2_0.25"], "44.25": ["Piano-left_B-2_0.25"], "44.5": ["Piano-left_B-3_0.25"], "44.75": ["Piano-left_B-2_0.25"], "45.0": ["Piano-left_G2_0.25"], "45.25": ["Piano-left_B-2_0.25"], "45.5": ["Piano-left_B-3_0.25"], "45.75": ["Piano-left_B-2_0.25"], "46.0": ["Piano-left_G#2_0.25"], "46.25": ["Piano-left_B-2_0.25"], "46.5": ["Piano-left_G#3_0.25"], "46.75": ["Piano-left_B-2_0.25"], "47.0": ["Piano-left_B-1_0.25"], "47.25": ["Piano-left_B-2_0.25"]}, "beethoven_opus22_1.mid": {"3.0": ["Piano-right_B-3_0.25", "Piano-right_D4_1.0"], "3.25": ["Piano-right_A3_0.25"], "3.5": ["Piano-right_B-3_0.25"], "3.75": ["Piano-right_F3_0.25"], "4.0": ["Piano-right_D4.F4_0.25", "Piano-left_B-1.B-2_0.25"], "5.0": ["Piano-right_B-3.D4_0.25", "Piano-left_B-1.B-2_0.25"], "7.0": ["Piano-right_B-3_0.25", "Piano-right_D4_1.0"], "7.25": ["Piano-right_A3_0.25"], "7.5": ["Piano-right_B-3_0.25"], "7.75": ["Piano-right_F3_0.25"], "8.0": ["Piano-right_D4.F4_0.25", "Piano-left_B-1.B-2_0.25"], "9.0": ["Piano-right_B-3.D4_0.25", "Piano-left_B-1.B-2_0.25"], "11.0": ["Piano-right_D4_0.5", "Piano-right_B-3_0.25"], "11.25": ["Piano-right_A3_0.25"], "11.5": ["Piano-right_B-3_0.25"], "11.75": ["Piano-right_F3_0.25"], "12.0": ["Piano-right_F4_0.5", "Piano-right_D4_0.25"], "12.25": ["Piano-right_C#4_0.25"], "12.5": ["Piano-right_D4_0.25"], "12.75": ["Piano-right_B-3_0.25"], "13.0": ["Piano-right_F4_0.25", "Piano-right_B-4_0.5"], "13.25": ["Piano-right_E4_0.25"], "13.5": ["Piano-right_F4_0.25"], "13.75": ["Piano-right_D4_0.25"], "14.0": ["Piano-right_B-4_0.25", "Piano-right_D5_0.5"], "14.25": ["Piano-right_A4_0.25"], "14.5": ["Piano-right_B-4_0.25"], "14.75": ["Piano-right_F4_0.25"], "15.0": ["Piano-right_D5_0.25", "Piano-right_F5_0.5"], "15.25": ["Piano-right_C#5_0.25"], "15.5": ["Piano-right_D5_0.25"], "15.75": ["Piano-right_B-4_0.25"], "16.0": ["Piano-right_B-5_3.0", "Piano-left_B-2_0.25"], "19.0": ["Piano-right_A5_0.25", "Piano-left_B-2_0.25"], "19.25": ["Piano-right_B-5_0.25", "Piano-left_D3_0.25"], "19.5": ["Piano-right_C6_0.25", "Piano-left_F3_0.25"], "19.75": ["Piano-right_B-5_0.25", "Piano-left_B-3_0.25"], "20.0": ["Piano-right_A5_0.5", "Piano-left_B-2_0.25"], "20.5": ["Piano-right_G5_0.5", "Piano-left_G3_0.25"], "21.0": ["Piano-right_F5_0.5", "Piano-left_B-2_0.25"], "21.5": ["Piano-right_E-5_0.5", "Piano-left_G3_0.25"], "22.0": ["Piano-right_D5_0.5", "Piano-left_B-2_0.25"], "22.5": ["Piano-right_C5_0.5", "Piano-left_F3_0.25"], "23.0": ["Piano-right_G5_0.5", "Piano-left_B-2_0.25"], "23.5": ["Piano-right_F5_0.5", "Piano-left_F3_0.25"], "24.0": ["Piano-right_E-5_1.0", "Piano-left_B-2_0.25"], "25.0": ["Piano-right_D5_1.0", "Piano-left_B-2_0.25"], "27.0": ["Piano-right_A4_0.25", "Piano-left_B-2_0.25"], "27.25": ["Piano-right_B-4_0.25", "Piano-left_D3_0.25"], "27.5": ["Piano-right_C5_0.25", "Piano-left_F3_0.25"], "27.75": ["Piano-right_B-4_0.25", "Piano-left_G#3_0.25"], "28.0": ["Piano-right_G#4_0.5", "Piano-left_B-2_0.25"], "28.5": ["Piano-right_G4_0.5", "Piano-left_G3_0.25"], "29.0": ["Piano-right_F4_0.5", "Piano-left_B-2_0.25"], "29.5": ["Piano-right_E-4_0.5", "Piano-left_G3_0.25"], "30.0": ["Piano-right_D4_0.5", "Piano-left_B-2_0.25"], "30.5": ["Piano-right_C4_0.5", "Piano-left_E-3_0.25"], "31.0": ["Piano-right_E-4_0.5", "Piano-left_B-2_0.25"], "31.5": ["Piano-right_A3_0.5", "Piano-left_E-3_0.25"], "32.0": ["Piano-right_B-3_0.25", "Piano-left_B-2_0.25"], "32.5": ["Piano-right_D4_0.25"], "32.75": ["Piano-right_C4_0.25"], "33.0": ["Piano-right_B-3_0.25", "Piano-left_B-2_0.25"], "33.25": ["Piano-right_A3_0.25", "Piano-left_A2_0.25"], "33.5": ["Piano-right_B-3_0.25", "Piano-left_B-2_0.25"], "33.75": ["Piano-right_G3_0.25", "Piano-left_G2_0.25"], "34.0": ["Piano-right_F3_0.25", "Piano-left_F2_0.25"], "34.5": ["Piano-right_G4_0.25"], "34.75": ["Piano-right_F4_0.25"], "35.0": ["Piano-right_E-4_0.25", "Piano-left_E-3_0.25"], "35.25": ["Piano-right_D4_0.25", "Piano-left_D3_0.25"], "35.5": ["Piano-right_E-4_0.25", "Piano-left_E-3_0.25"], "35.75": ["Piano-right_C4_0.25", "Piano-left_C3_0.25"], "36.0": ["Piano-right_B-3_0.25", "Piano-left_B-2_0.25"], "36.5": ["Piano-right_D5_0.25"], "36.75": ["Piano-right_C5_0.25"], "37.0": ["Piano-right_B-4_0.25", "Piano-left_B-3_0.25"], "37.25": ["Piano-right_A4_0.25", "Piano-left_A3_0.25"], "37.5": ["Piano-right_B-4_0.25", "Piano-left_B-3_0.25"], "37.75": ["Piano-right_G4_0.25", "Piano-left_G3_0.25"], "38.0": ["Piano-right_F4_0.25", "Piano-left_F3_0.25"], "38.5": ["Piano-right_G5_0.25"], "38.75": ["Piano-right_F5_0.25"], "39.0": ["Piano-right_E-5_0.25", "Piano-left_E-4_0.25"], "39.25": ["Piano-right_D5_0.25", "Piano-left_D4_0.25"], "39.5": ["Piano-right_E-5_0.25", "Piano-left_E-4_0.25"], "39.75": ["Piano-right_C5_0.25", "Piano-left_C4_0.25"], "40.0": ["Piano-right_B-4_0.25", "Piano-left_B-3_0.25"], "40.5": ["Piano-right_C5_0.25", "Piano-left_C4_0.25"], "40.75": ["Piano-right_D5_0.25", "Piano-left_D4_0.25"], "41.0": ["Piano-right_E-5_0.25", "Piano-left_E-4_0.25"], "41.25": ["Piano-right_F5_0.25", "Piano-left_F4_0.25"], "41.5": ["Piano-right_G5_0.25", "Piano-left_G4_0.25"], "16.25": ["Piano-left_D3_0.25"], "16.5": ["Piano-left_F3_0.25"], "16.75": ["Piano-left_B-3_0.25"], "17.0": ["Piano-left_B-2_0.25"], "17.25": ["Piano-left_D3_0.25"], "17.5": ["Piano-left_F3_0.25"], "17.75": ["Piano-left_B-3_0.25"], "18.0": ["Piano-left_B-2_0.25"], "18.25": ["Piano-left_D3_0.25"], "18.5": ["Piano-left_F3_0.25"], "18.75": ["Piano-left_B-3_0.25"], "20.25": ["Piano-left_E-3_0.25"], "20.75": ["Piano-left_B-3_0.25"], "21.25": ["Piano-left_E-3_0.25"], "21.75": ["Piano-left_B-3_0.25"], "22.25": ["Piano-left_E-3_0.25"], "22.75": ["Piano-left_A3_0.25"], "23.25": ["Piano-left_E-3_0.25"], "23.75": ["Piano-left_A3_0.25"], "24.25": ["Piano-left_D3_0.25"], "24.5": ["Piano-left_F3_0.25"], "24.75": ["Piano-left_B-3_0.25"], "25.25": ["Piano-left_D3_0.25"], "25.5": ["Piano-left_F3_0.25"], "25.75": ["Piano-left_B-3_0.25"], "26.0": ["Piano-left_B-2_0.25"], "26.25": ["Piano-left_D3_0.25"], "26.5": ["Piano-left_F3_0.25"], "26.75": ["Piano-left_G#3_0.25"], "28.25": ["Piano-left_E-3_0.25"], "28.75": ["Piano-left_E-3_0.25"], "29.25": ["Piano-left_E-3_0.25"], "29.75": ["Piano-left_E-3_0.25"], "30.25": ["Piano-left_C3_0.25"], "30.75": ["Piano-left_F3_0.25"], "31.25": ["Piano-left_C3_0.25"], "31.75": ["Piano-left_F3_0.25"], "41.75": ["Piano-left_A4_0.25"], "42.0": ["Piano-left_B-4_0.25"], "42.25": ["Piano-left_A4_0.25"], "42.5": ["Piano-left_B-4_0.25"], "42.75": ["Piano-left_C5_0.25"], "43.0": ["Piano-left_D5_0.25"]}, "beethoven_opus22_2.mid": {"3.0": ["Piano-right_G4_1/3", "Piano-left_E-3.G3.B-3_0.5"], "10/3": ["Piano-right_G#4_0.25"], "3.5": ["Piano-right_G4_0.25", "Piano-left_E-3.G3.B-3_0.5"], "3.75": ["Piano-right_F4_0.25"], "4.0": ["Piano-right_G4_0.25", "Piano-left_E-3.G3.B-3_0.5"], "4.25": ["Piano-right_G#4_0.25"], "4.5": ["Piano-right_A4_1.5", "Piano-left_E-3.G3.B-3_0.5"], "6.0": ["Piano-right_B-4_1.75", "Piano-left_E-3.G3.B-3_0.5"], "7.75": ["Piano-right_C5_0.25"], "8.0": ["Piano-right_B-4_0.25", "Piano-left_E-3.G3.B-3_0.5"], "8.25": ["Piano-right_A4_0.25"], "8.5": ["Piano-right_B-4_0.25", "Piano-left_E-3.G3.B-3_0.5"], "8.75": ["Piano-right_B4_0.25"], "9.0": ["Piano-right_B4_0.75", "Piano-left_D3.G#3.B-3_0.5"], "9.75": ["Piano-right_C5.B4_0.0", "Piano-right_A4.B4_0.0"], "10.0": ["Piano-right_D5_1/3", "Piano-left_D3.G#3.B-3_0.5"], "31/3": ["Piano-right_C5_0.25"], "10.5": ["Piano-right_F4_1.75", "Piano-left_D3.G#3.B-3_0.5"], "37/3": ["Piano-right_G4_0.25"], "12.5": ["Piano-right_F4_0.25", "Piano-left_D3.G#3.B-3_0.5"], "12.75": ["Piano-right_E4_0.25"], "13.0": ["Piano-right_F4_0.25", "Piano-left_D3.G#3.B-3_0.5"], "13.25": ["Piano-right_G4_0.25"], "13.5": ["Piano-right_G#4_1.75", "Piano-left_F3.D3.G#3.B-3_0.5"], "15.25": ["Piano-right_G4_0.25"], "15.5": ["Piano-right_F4_0.25", "Piano-left_F3.D3.G#3.B-3_0.5"], "15.75": ["Piano-right_E4_0.25"], "16.0": ["Piano-right_F4_0.25", "Piano-left_F3.D3.G#3.B-3_0.5"], "16.25": ["Piano-right_G4_0.25"], "16.5": ["Piano-right_G#4_0.25", "Piano-left_F3.D3.G#3.B-3_0.5"], "16.75": ["Piano-right_B-4_0.25"], "17.0": ["Piano-right_C5_0.25", "Piano-left_F3.D3.G#3.B-3_0.5"], "17.25": ["Piano-right_B4_0.25"], "17.5": ["Piano-right_C5_0.25", "Piano-left_F3.D3.G#3.B-3_0.5"], "17.75": ["Piano-right_G#4_0.25"], "18.0": ["Piano-right_F#4_1.5", "Piano-left_E-3.G#3.B-3_0.5"], "19.5": ["Piano-right_G4_1.75", "Piano-left_E-3.G3.B-3_0.5"], "21.25": ["Piano-right_E-4_0.25"], "21.5": ["Piano-right_G4_0.25", "Piano-left_B-2_0.5"], "21.75": ["Piano-right_B-4_0.25"], "22.0": ["Piano-right_E-5_0.25", "Piano-left_G#2_0.5"], "22.25": ["Piano-right_G5_0.25"], "22.5": ["Piano-right_B-5_2.0", "Piano-left_G2_0.5"], "24.5": ["Piano-right_G5_0.5", "Piano-left_G2.B-2.E-3_0.5"], "25.0": ["Piano-right_E-5_0.5", "Piano-left_G2.B-2.E-3_0.5"], "25.5": ["Piano-right_B-4_0.5", "Piano-left_G2.B-2.E-3_0.5"], "26.0": ["Piano-right_G4_0.5", "Piano-left_G2.B-2.E-3_0.5"], "26.5": ["Piano-right_E-4_0.5", "Piano-left_G2.B-2.E-3_0.5"], "27.0": ["Piano-right_C4_1.5", "Piano-left_G#2.C3.E-3_0.5"], "28.5": ["Piano-right_C6_2.0", "Piano-left_G#2.C3.E3_0.5"], "30.5": ["Piano-right_B-5_0.25", "Piano-left_G#2.C3.F3_0.5"], "30.75": ["Piano-right_G#5_0.25"], "31.0": ["Piano-right_G5_0.25", "Piano-left_G#2.C3.F3_0.5"], "31.25": ["Piano-right_F5_0.25"], "31.5": ["Piano-right_F5_0.5", "Piano-left_B-2.E-3.G3_0.5"], "32.0": ["Piano-right_E-5_1.5", "Piano-left_B-2.E-3.G3_0.5"], "33.5": ["Piano-right_E-5_0.5", "Piano-left_B-2.E-3.G3_0.5"], "34.0": ["Piano-right_E-5_0.5", "Piano-left_B-2.E-3.G3_0.5"], "34.5": ["Piano-right_E-5.F5_0.0", "Piano-left_B-2.F3.G#3_0.5"], "104/3": ["Piano-right_E-5.F5_0.0"], "34.75": ["Piano-right_E-5.F5_0.0", "Piano-right_E-5.D5_0.0"], "35.0": ["Piano-right_E-5_0.25", "Piano-right_F5_0.5", "Piano-left_B-2.F3.G#3_0.5"], "35.5": ["Piano-right_D5_0.5", "Piano-left_B-2.F3.G#3_0.5"], "36.0": ["Piano-right_E-5_0.5", "Piano-left_E-3.G3_1.0"], "36.5": ["Piano-right_B-4_0.5"], "37.0": ["Piano-right_B-4_0.5"], "37.5": ["Piano-right_B-4_0.5"], "38.0": ["Piano-right_C5_0.5"], "38.5": ["Piano-right_G#4_0.5"], "39.0": ["Piano-right_E-4_1.0", "Piano-right_G4_0.5", "Piano-left_B-2_1.5", "Piano-left_B-3_1.0"], "39.5": ["Piano-right_G#4_0.5"], "40.0": ["Piano-right_D4.F4_0.5", "Piano-left_G#3_0.5"], "40.5": ["Piano-right_E-4_0.5", "Piano-left_E-3.G3_1.0"], "41.0": ["Piano-right_B-3_0.5"], "41.5": ["Piano-right_B-3_0.5"], "42.0": ["Piano-right_B-3.C4_0.0", "Piano-right_B-3.C4_0.0"], "42.25": ["Piano-right_B-3.C4_0.0"], "127/3": ["Piano-right_B-3.A3_0.0"], "42.5": ["Piano-right_B-3_0.25", "Piano-right_C4_0.5"], "43.0": ["Piano-right_G#3_0.5"], "43.5": ["Piano-right_G3.G#3_0.0", "Piano-right_E-3_1.0", "Piano-left_B-2_1.0", "Piano-left_B-1_1.5"], "131/3": ["Piano-right_G3.G#3_0.0"], "43.75": ["Piano-right_G3.G#3_0.0", "Piano-right_G3.F3_0.0"], "44.0": ["Piano-right_G3_0.25", "Piano-right_G#3_0.5"], "44.5": ["Piano-right_F3_0.5", "Piano-left_G#2.F3_0.5"], "45.0": ["Piano-right_E-3_1.0", "Piano-left_E-2.G2_1.0"], "46.0": ["Piano-right_D3.F3_0.5", "Piano-left_B-1.G#2_0.5"], "46.5": ["Piano-right_E-3_1.0", "Piano-left_E-2.G2_1.0"], "47.5": ["Piano-right_D3.F3_0.5", "Piano-left_B-1.G#2_0.5"], "48.0": ["Piano-right_E-3_1.0", "Piano-left_E-2.G2_1.0"], "49.0": ["Piano-right_D3.F3.B-3_0.5", "Piano-left_B-1.G#2_0.5"], "0.0": ["Piano-left_E-3.G3.B-3_0.5"], "0.5": ["Piano-left_E-3.G3.B-3_0.5"], "1.0": ["Piano-left_E-3.G3.B-3_0.5"], "1.5": ["Piano-left_E-3.G3.B-3_0.5"], "2.0": ["Piano-left_E-3.G3.B-3_0.5"], "2.5": ["Piano-left_E-3.G3.B-3_0.5"], "5.0": ["Piano-left_E-3.G3.B-3_0.5"], "5.5": ["Piano-left_E-3.G3.B-3_0.5"], "6.5": ["Piano-left_E-3.G3.B-3_0.5"], "7.0": ["Piano-left_E-3.G3.B-3_0.5"], "7.5": ["Piano-left_E-3.G3.B-3_0.5"], "9.5": ["Piano-left_D3.G#3.B-3_0.5"], "11.0": ["Piano-left_D3.G#3.B-3_0.5"], "11.5": ["Piano-left_D3.G#3.B-3_0.5"], "12.0": ["Piano-left_D3.G#3.B-3_0.5"], "14.0": ["Piano-left_F3.D3.G#3.B-3_0.5"], "14.5": ["Piano-left_F3.D3.G#3.B-3_0.5"], "15.0": ["Piano-left_F3.D3.G#3.B-3_0.5"], "18.5": ["Piano-left_E-3.G#3.B-3_0.5"], "19.0": ["Piano-left_E-3.G#3.B-3_0.5"], "20.0": ["Piano-left_E-3.G3.B-3_0.5"], "20.5": ["Piano-left_E-3.G3.B-3_0.5"], "21.0": ["Piano-left_E-3_0.5"], "23.0": ["Piano-left_G2.B-2.E-3_0.5"], "23.5": ["Piano-left_G2.B-2.E-3_0.5"], "24.0": ["Piano-left_G2.B-2.E-3_0.5"], "27.5": ["Piano-left_G#2.C3.E-3_0.5"], "28.0": ["Piano-left_G#2.C3.E-3_0.5"], "29.0": ["Piano-left_G#2.C3.E3_0.5"], "29.5": ["Piano-left_G#2.C3.E3_0.5"], "30.0": ["Piano-left_G#2.C3.F3_0.5"], "32.5": ["Piano-left_B-2.E-3.G3_0.5"], "33.0": ["Piano-left_B-2.E-3.G3_0.5"], "49.5": ["Piano-left_E-2.G#2_1.5"], "51.0": ["Piano-left_E-2.G2_1.0"], "54.0": ["Piano-left_E-2_0.5"], "54.5": ["Piano-left_G2_0.5"], "55.0": ["Piano-left_B-2_0.5"], "55.5": ["Piano-left_E-3_0.5"], "56.0": ["Piano-left_G3_0.5"], "56.5": ["Piano-left_B-3_0.5"], "57.0": ["Piano-left_B-2.B-3_1.0"], "58.0": ["Piano-left_B-2.G#3_0.5"], "58.5": ["Piano-left_E-3_2.0", "Piano-left_G#3_1.5"], "60.0": ["Piano-left_G3_0.5"], "63.0": ["Piano-left_E-2_0.5"]}, "beethoven_hammerklavier_4.mid": {"0.5": ["Piano-right_F4_0.25"], "2/3": ["Piano-right_F4_0.25"], "0.75": ["Piano-right_F5_0.25"], "1.0": ["Piano-right_F5_0.25"], "1.25": ["Piano-right_F6_1.0"], "1.5": ["Piano-right_F5_0.75"], "2.25": ["Piano-right_F6.F5_0.75"], "4.25": ["Piano-right_C#6.F6.G#5.F5_0.75"], "6.25": ["Piano-right_F6.B-5.F5.C#6_0.75"], "8.25": ["Piano-right_B-5.F#5.F#6.C#6_1.25"], "10.25": ["Piano-right_C#5_0.25"], "10.5": ["Piano-right_F#5_0.25"], "10.75": ["Piano-right_C#5_0.25"], "11.0": ["Piano-right_F#5_0.25"], "11.25": ["Piano-right_C#5_0.25"], "11.5": ["Piano-right_F#5_0.25"], "11.75": ["Piano-right_B-4_0.25"], "12.0": ["Piano-right_E-5_2.0"], "12.25": ["Piano-right_F#4_0.25"], "12.5": ["Piano-right_B4_0.25"], "12.75": ["Piano-right_F#4_0.25"], "13.0": ["Piano-right_B4_0.25"], "13.25": ["Piano-right_F#4_0.25"], "13.5": ["Piano-right_B4_0.25"], "13.75": ["Piano-right_E-4_0.25"], "14.0": ["Piano-right_E-5_0.5", "Piano-right_F4_0.25"], "14.25": ["Piano-right_G#4_0.25", "Piano-left_F3_0.25"], "14.5": ["Piano-right_C#5_1.0", "Piano-right_F4_0.25", "Piano-left_G#3_0.25"], "14.75": ["Piano-right_G#4_0.25", "Piano-left_F3_0.25"], "15.0": ["Piano-right_F4_0.25", "Piano-left_G#3_0.25"], "15.25": ["Piano-right_G#4_0.25", "Piano-left_F3_0.25"], "15.5": ["Piano-right_F4_0.25", "Piano-right_B4_0.5", "Piano-left_G#3_0.25"], "15.75": ["Piano-right_G#4_0.25", "Piano-left_C#3_0.25"], "16.0": ["Piano-right_F#4.B-4_0.5", "Piano-left_F#3_0.5"], "16.5": ["Piano-right_A4.F#4.E-5_0.5", "Piano-left_C3_0.5"], "17.0": ["Piano-right_F4.G#4_0.75", "Piano-left_C#3_0.5"], "17.75": ["Piano-right_F#4.B-4_0.25"], "18.0": ["Piano-right_F#5.B-5.B-4.C#5_0.5"], "19.25": ["Piano-right_F#5.B-4.E-5.B-5_0.75"], "20.75": ["Piano-right_F#5.E-6.E-5_0.5"], "23.25": ["Piano-right_F#4_0.25", "Piano-left_B3_0.25"], "23.5": ["Piano-right_G#4_0.25", "Piano-left_F#4_0.25"], "23.75": ["Piano-right_B-4_0.25", "Piano-left_E4_0.25"], "24.0": ["Piano-right_B4_0.25", "Piano-left_E-4_0.25"], "24.25": ["Piano-right_C#5_0.25", "Piano-left_C#4_0.25"], "24.5": ["Piano-right_E-5_0.25", "Piano-left_B3_0.25"], "24.75": ["Piano-right_E5_0.25", "Piano-left_B-3_0.25"], "25.0": ["Piano-right_E-5_0.25", "Piano-left_B3_0.25"], "25.25": ["Piano-right_B4_0.25", "Piano-left_F#3_0.25"], "25.5": ["Piano-right_F#5_0.25", "Piano-left_G#3_0.25"], "25.75": ["Piano-right_E5_0.25", "Piano-left_B-3_0.25"], "26.0": ["Piano-right_E-5_0.25", "Piano-left_B3_0.25"], "26.25": ["Piano-right_C#5_0.25", "Piano-left_C#4_0.25"], "26.5": ["Piano-right_B4_0.25", "Piano-left_E-4_0.25"], "26.75": ["Piano-right_B-4_0.25", "Piano-left_E4_0.25"], "27.0": ["Piano-right_B4_0.25", "Piano-left_E-4_0.25"], "27.25": ["Piano-right_F#5_0.25", "Piano-left_E-5_0.25"], "27.5": ["Piano-right_G#5_0.25", "Piano-left_F#5_0.25"], "27.75": ["Piano-right_B-5_0.25", "Piano-left_E5_0.25"], "28.0": ["Piano-right_B5_0.25", "Piano-left_E-5_0.25"], "28.25": ["Piano-right_C#6_0.25", "Piano-left_C#5_0.25"], "28.5": ["Piano-right_E-6_0.25", "Piano-left_B4_0.25"], "28.75": ["Piano-right_E6_0.25", "Piano-left_B-4_0.25"], "29.0": ["Piano-right_E-6_0.25", "Piano-left_B4_0.25"], "29.25": ["Piano-right_C#6_0.25", "Piano-left_B-4_0.25"], "29.5": ["Piano-right_B5_0.25", "Piano-left_E-5_0.25"], "29.75": ["Piano-right_B-5_0.25", "Piano-left_C#5_0.25"], "30.0": ["Piano-right_G#5_0.25", "Piano-left_B4_0.25"], "30.25": ["Piano-right_F#5_0.25", "Piano-left_B-4_0.25"], "30.5": ["Piano-right_E5_0.25", "Piano-left_G#4_0.25"], "30.75": ["Piano-right_E-5_0.25", "Piano-left_F#4_0.25"], "31.0": ["Piano-right_C#5_0.25", "Piano-left_E4_0.25"], "31.25": ["Piano-right_B4_0.25", "Piano-left_E-4_0.25"], "31.5": ["Piano-right_B-4_0.25", "Piano-left_C#4_0.25"], "31.75": ["Piano-right_G#4_0.25", "Piano-left_B3_0.25"], "32.0": ["Piano-right_F#4_0.25", "Piano-left_B-3_0.25"], "32.25": ["Piano-right_E5_0.25", "Piano-left_C#4_0.25"], "32.5": ["Piano-right_E-5_0.25", "Piano-left_B3_0.25"], "32.75": ["Piano-right_G#5_0.25", "Piano-left_E4_0.25"], "33.0": ["Piano-right_F#5_0.25", "Piano-left_E-4_0.25"], "33.25": ["Piano-right_B5_0.25", "Piano-left_D4_0.25"], "33.5": ["Piano-right_B-5_0.25", "Piano-left_C#4_0.25"], "33.75": ["Piano-right_E6_0.25", "Piano-left_F#3_0.25"], "34.0": ["Piano-right_E5.B-5.E6_0.75", "Piano-left_C#4.F#4.F#3_0.75"], "34.75": ["Piano-right_B5.E-6.F#5.E-5_0.75"], "36.75": ["Piano-right_E-5.B5.E-6.G#5_0.5"], "37.25": ["Piano-right_E-5_0.25"], "37.5": ["Piano-right_G#4_0.25"], "37.75": ["Piano-right_E-5_0.25"], "38.0": ["Piano-right_E5_0.25"], "38.25": ["Piano-right_E-5_0.25"], "38.5": ["Piano-right_G#4_0.25"], "38.75": ["Piano-right_E-5_0.25"], "39.0": ["Piano-right_E5_2.25"], "41.25": ["Piano-right_B-4_0.25"], "41.5": ["Piano-right_E-5_0.25"], "41.75": ["Piano-right_D5_0.25"], "0.0": ["Piano-left_F2_0.25"], "0.25": ["Piano-left_F3_0.25"], "1/3": ["Piano-left_F3_0.25"], "4/3": ["Piano-left_F1.F2_1.0"], "3.0": ["Piano-left_F2.F3_0.5"], "5.0": ["Piano-left_C#2.C#3_0.5"], "7.0": ["Piano-left_B-1.B-2_0.5"], "9.0": ["Piano-left_F#1.F#2_0.5"], "17.5": ["Piano-left_F#2_0.5"], "18.5": ["Piano-left_F#3.F#2_0.5"], "20.0": ["Piano-left_E-3.E-2_0.5"], "21.0": ["Piano-left_B1.B2_0.25"], "21.25": ["Piano-left_F#3_0.25"], "21.5": ["Piano-left_G#3_0.25"], "21.75": ["Piano-left_B-3_0.25"], "22.0": ["Piano-left_B3_0.25"], "22.25": ["Piano-left_C#4_0.25"], "22.5": ["Piano-left_E-4_0.25"], "22.75": ["Piano-left_E4_0.25"], "23.0": ["Piano-left_E-4_0.25"], "35.5": ["Piano-left_B2.B1_0.5"], "37.0": ["Piano-left_G#1.G#2_0.5"], "39.25": ["Piano-left_G#4_0.25"], "39.5": ["Piano-left_C#4_0.25"], "39.75": ["Piano-left_G#4_0.25"], "40.0": ["Piano-left_B-4_0.25"], "40.25": ["Piano-left_G#4_0.25"], "40.5": ["Piano-left_C#4_0.25"], "40.75": ["Piano-left_G#4_0.25"], "41.0": ["Piano-left_G4_1.5"], "42.5": ["Piano-left_G4_1.0"], "43.5": ["Piano-left_G4_0.5"], "44.0": ["Piano-left_E4_0.5"], "44.5": ["Piano-left_E-4_0.5"], "45.0": ["Piano-left_C#4_0.25"], "45.25": ["Piano-left_G#3_0.25"], "45.5": ["Piano-left_C#3_0.25"], "45.75": ["Piano-left_G#3_0.25"], "46.0": ["Piano-left_A3_0.25"], "46.25": ["Piano-left_G#3_0.25"], "46.5": ["Piano-left_C#3_0.25"], "46.75": ["Piano-left_G#3_0.25"], "47.0": ["Piano-left_A3_1.5"], "48.5": ["Piano-left_G#3_0.5"], "49.0": ["Piano-left_B-3_0.25", "Piano-left_G3_2.0"]}, "beethoven_opus22_3.mid": {"2.0": ["Piano-right_D4_0.75"], "2.75": ["Piano-right_E-4_0.25"], "3.0": ["Piano-right_F4_2.0", "Piano-left_B-2_0.25"], "5.0": ["Piano-right_A4_0.25", "Piano-right_G4_0.25", "Piano-left_E-4_0.5"], "5.25": ["Piano-right_F4_0.25"], "5.5": ["Piano-right_G4_0.25", "Piano-left_C4_0.5"], "5.75": ["Piano-right_A4_0.25"], "6.0": ["Piano-right_B-4_1.0", "Piano-left_D4_0.5"], "7.0": ["Piano-right_F4_0.75", "Piano-left_D4_0.5"], "8.0": ["Piano-right_A4_0.25", "Piano-right_G4_0.25", "Piano-left_E-4_0.5"], "8.25": ["Piano-right_F4_0.25"], "8.5": ["Piano-right_G4_0.25", "Piano-left_C4_0.5"], "8.75": ["Piano-right_A4_0.25"], "9.0": ["Piano-right_B-4_0.25", "Piano-left_D4_0.5"], "9.75": ["Piano-right_A4_0.25"], "10.0": ["Piano-right_B-4_0.25", "Piano-left_D4_0.5"], "10.75": ["Piano-right_C5_0.25"], "11.0": ["Piano-right_D5_0.25", "Piano-left_B-3_0.5"], "11.75": ["Piano-right_E5_0.25"], "12.0": ["Piano-right_B-4.E5_1.0", "Piano-left_F3_1.5"], "13.0": ["Piano-right_A4.F5_0.5", "Piano-left_F4_0.5"], "14.0": ["Piano-right_F5_0.25", "Piano-right_E-5_0.25"], "14.25": ["Piano-right_D5_0.25"], "14.5": ["Piano-right_E-5_0.25"], "14.75": ["Piano-right_F5_0.25"], "15.0": ["Piano-right_G5_1.0"], "16.0": ["Piano-right_C5_0.75", "Piano-left_A3_0.5"], "17.0": ["Piano-right_D5_0.25", "Piano-right_C5_0.25", "Piano-left_E-4_1.5"], "17.25": ["Piano-right_B4_0.25"], "17.5": ["Piano-right_C5_0.25"], "17.75": ["Piano-right_D5_0.25"], "18.0": ["Piano-right_E-5_1.0"], "19.0": ["Piano-right_A4_0.75", "Piano-left_C4_0.5"], "20.0": ["Piano-right_B-4_0.25", "Piano-right_A4_0.25", "Piano-left_F#4_2.0"], "20.25": ["Piano-right_G4_0.25"], "20.5": ["Piano-right_A4_0.25"], "20.75": ["Piano-right_B-4_0.25"], "21.0": ["Piano-right_D5_0.25", "Piano-right_C5_0.25"], "21.25": ["Piano-right_B4_0.25"], "21.5": ["Piano-right_C5_0.25"], "21.75": ["Piano-right_D5_0.25"], "22.0": ["Piano-right_F5_0.25", "Piano-right_E-5_0.25", "Piano-left_F4.F3_1.0"], "22.25": ["Piano-right_D5_0.25"], "22.5": ["Piano-right_E-5_0.25"], "22.75": ["Piano-right_F5_0.25"], "23.0": ["Piano-right_G5_0.25", "Piano-left_F3.E-4_1.0"], "23.75": ["Piano-right_A4_0.25"], "24.0": ["Piano-right_C5_1.0", "Piano-left_B-3_1.5", "Piano-left_E-4_1.0"], "25.0": ["Piano-right_B-4_0.5", "Piano-left_D4_0.5"], "26.0": ["Piano-right_D4_0.75"], "26.75": ["Piano-right_E-4_0.25"], "27.0": ["Piano-right_F4_2.0", "Piano-left_B-2_0.25"], "29.0": ["Piano-right_A4_0.25", "Piano-right_G4_0.25", "Piano-left_E-4_0.5"], "29.25": ["Piano-right_F4_0.25"], "29.5": ["Piano-right_G4_0.25", "Piano-left_C4_0.5"], "29.75": ["Piano-right_A4_0.25"], "30.0": ["Piano-right_B-4_1.0", "Piano-left_D4_0.5"], "31.0": ["Piano-right_F4_0.75", "Piano-left_D4_0.5"], "32.0": ["Piano-right_A4_0.25", "Piano-right_G4_0.25", "Piano-left_E-4_0.5"], "32.25": ["Piano-right_F4_0.25"], "32.5": ["Piano-right_G4_0.25", "Piano-left_C4_0.5"], "32.75": ["Piano-right_A4_0.25"], "33.0": ["Piano-right_B-4_0.25", "Piano-left_D4_0.5"], "33.75": ["Piano-right_A4_0.25"], "34.0": ["Piano-right_B-4_0.25", "Piano-left_D4_0.5"], "34.75": ["Piano-right_C5_0.25"], "35.0": ["Piano-right_D5_0.25", "Piano-left_B-3_0.5"], "35.75": ["Piano-right_E5_0.25"], "36.0": ["Piano-right_B-4.E5_1.0", "Piano-left_F3_1.5"], "37.0": ["Piano-right_A4.F5_0.5", "Piano-left_F4_0.5"], "38.0": ["Piano-right_F5_0.25", "Piano-right_E-5_0.25"], "38.25": ["Piano-right_D5_0.25"], "38.5": ["Piano-right_E-5_0.25"], "38.75": ["Piano-right_F5_0.25"], "39.0": ["Piano-right_G5_1.0"], "40.0": ["Piano-right_C5_0.75", "Piano-left_A3_0.5"], "41.0": ["Piano-right_D5_0.25", "Piano-right_C5_0.25", "Piano-left_E-4_1.5"], "41.25": ["Piano-right_B4_0.25"], "41.5": ["Piano-right_C5_0.25"], "41.75": ["Piano-right_D5_0.25"], "42.0": ["Piano-right_E-5_1.0"], "43.0": ["Piano-right_A4_0.75", "Piano-left_C4_0.5"], "44.0": ["Piano-right_B-4_0.25", "Piano-right_A4_0.25", "Piano-left_F#4_2.0"], "44.25": ["Piano-right_G4_0.25"], "44.5": ["Piano-right_A4_0.25"], "44.75": ["Piano-right_B-4_0.25"], "45.0": ["Piano-right_D5_0.25", "Piano-right_C5_0.25"], "3.5": ["Piano-left_B-3_0.5"], "4.0": ["Piano-left_D4_0.5"], "4.5": ["Piano-left_B-3_0.5"], "6.5": ["Piano-left_C#4_0.5"], "7.5": ["Piano-left_B-3_0.5"], "9.5": ["Piano-left_C#4_0.5"], "10.5": ["Piano-left_A3_0.5"], "11.5": ["Piano-left_G3_0.5"], "15.5": ["Piano-left_F3_3.0"], "16.5": ["Piano-left_C4_0.5"], "18.5": ["Piano-left_F3_3.5"], "19.5": ["Piano-left_E-4_0.5"], "27.5": ["Piano-left_B-3_0.5"], "28.0": ["Piano-left_D4_0.5"], "28.5": ["Piano-left_B-3_0.5"], "30.5": ["Piano-left_C#4_0.5"], "31.5": ["Piano-left_B-3_0.5"], "33.5": ["Piano-left_C#4_0.5"], "34.5": ["Piano-left_A3_0.5"], "35.5": ["Piano-left_G3_0.5"], "39.5": ["Piano-left_F3_3.0"], "40.5": ["Piano-left_C4_0.5"], "42.5": ["Piano-left_F3_3.5"], "43.5": ["Piano-left_E-4_0.5"], "46.0": ["Piano-left_F4.F3_1.0"], "47.0": ["Piano-left_F3.E-4_1.0"], "48.0": ["Piano-left_B-3_1.5", "Piano-left_E-4_1.0"], "49.0": ["Piano-left_D4_0.5"], "50.0": ["Piano-left_F#4_0.25"], "50.25": ["Piano-left_G4_0.25"], "50.5": ["Piano-left_F#4_0.25"], "50.75": ["Piano-left_G4_0.25"], "51.0": ["Piano-left_F#4_0.25"], "51.25": ["Piano-left_G4_0.25"], "51.5": ["Piano-left_F#4_0.25"], "51.75": ["Piano-left_G4_0.25"], "52.0": ["Piano-left_F#4_0.25"], "52.25": ["Piano-left_G4_0.25"], "52.5": ["Piano-left_F#4_0.25"], "52.75": ["Piano-left_G4_0.25"], "53.0": ["Piano-left_F#4_0.25"], "53.25": ["Piano-left_G4_0.25"], "53.5": ["Piano-left_F#4_0.25"], "53.75": ["Piano-left_G4_0.25"], "54.0": ["Piano-left_F#4_0.5"], "55.0": ["Piano-left_D3.D4_1.5"], "56.5": ["Piano-left_D3.D4_0.25"], "57.0": ["Piano-left_E-3.E-4_0.5"], "57.75": ["Piano-left_C3.C4_0.25"], "58.0": ["Piano-left_D3.D4_0.5"], "59.0": ["Piano-left_D2.D3_0.5"], "60.0": ["Piano-left_G2.G3_1.5"], "62.0": ["Piano-left_D3_0.25"], "62.25": ["Piano-left_E-3_0.25"], "62.5": ["Piano-left_D3_0.25"], "62.75": ["Piano-left_E-3_0.25"], "63.0": ["Piano-left_D3_0.25"], "63.25": ["Piano-left_E-3_0.25"], "63.5": ["Piano-left_D3_0.25"], "63.75": ["Piano-left_E-3_0.25"], "64.0": ["Piano-left_D3_0.25"], "64.25": ["Piano-left_E-3_0.25"]}, "beethoven_hammerklavier_1.mid": {"2.75": ["Piano-right_D5.F5.B-5.D6_0.25", "Piano-left_F3.D4.B-3_0.25"], "3.0": ["Piano-right_F5.B-5.D5.D6_1/3", "Piano-left_D4.B-3.F3_1/3"], "3.5": ["Piano-right_D5.E-6.F5.B-5_0.25", "Piano-left_D4.B-3.F3_0.25"], "3.75": ["Piano-right_D6.D5.B-5.F5_0.25", "Piano-left_B-3.D4.F3_0.25"], "4.0": ["Piano-right_F5.D5.B-5.D6_0.25", "Piano-left_D4.F3.B-3_0.25"], "4.5": ["Piano-right_D5.B-4.F5.B-5_0.25", "Piano-left_F3.D3.B-3_0.25"], "6.75": ["Piano-right_B-5.D6.F5.F6_0.25", "Piano-left_B-3.F3.D4.F4_0.25"], "7.0": ["Piano-right_F5.B-5.D6.F6_1/3", "Piano-left_B-3.F4.D4.F3_1/3"], "7.5": ["Piano-right_B-5.D6.G6.F5_0.25", "Piano-left_D4.B-3.F4.F3_0.25"], "7.75": ["Piano-right_F5.B-5.F6.D6_0.25", "Piano-left_D4.B-3.F4.F3_0.25"], "8.0": ["Piano-right_F6.F5.B-5.D6_0.25", "Piano-left_B-3.F4.F3.D4_0.25"], "8.5": ["Piano-right_D5.F5.B-5.D6_0.25", "Piano-left_B-3.D4.F3_0.25"], "9.5": ["Piano-right_B-4_0.25"], "9.75": ["Piano-right_C5_0.25"], "10.0": ["Piano-right_D5_1.0"], "10.5": ["Piano-right_G4_0.5", "Piano-left_E4_0.5"], "11.0": ["Piano-right_A4.C5_0.5", "Piano-left_F4_0.5"], "11.5": ["Piano-right_G#4_0.5", "Piano-right_C5_0.25", "Piano-left_B3_0.5"], "11.75": ["Piano-right_D5_0.25"], "12.0": ["Piano-right_E-5_1.0", "Piano-right_G4_0.5", "Piano-left_C4_0.5"], "12.5": ["Piano-right_A4_0.5", "Piano-left_F#3_0.5"], "13.0": ["Piano-right_B-4.D5_0.5", "Piano-left_G3_0.5"], "13.5": ["Piano-right_G4_0.5", "Piano-right_D5_0.25", "Piano-left_E-3_0.5"], "13.75": ["Piano-right_E-5_0.25"], "14.0": ["Piano-right_F4_0.5", "Piano-right_F5_0.75", "Piano-left_D3_0.5"], "14.5": ["Piano-right_B-4_0.5", "Piano-left_C#3_0.5"], "14.75": ["Piano-right_G5_0.25"], "15.0": ["Piano-right_G4_0.5", "Piano-right_F5_0.25", "Piano-left_C3_0.5"], "15.25": ["Piano-right_E-5_0.5"], "15.5": ["Piano-right_A4_0.5", "Piano-left_F2_0.5"], "15.75": ["Piano-right_F5_0.25"], "16.0": ["Piano-right_B-4.F4_0.5", "Piano-right_E-5_0.25", "Piano-left_B-2_0.5"], "16.25": ["Piano-right_D5_0.25"], "16.5": ["Piano-right_C5.G4_0.5", "Piano-right_F5_0.25", "Piano-left_E-2_0.5"], "16.75": ["Piano-right_E-5_0.25"], "17.0": ["Piano-right_A4.C5_0.5", "Piano-left_F2_0.5"], "17.5": ["Piano-right_B-5_0.25"], "17.75": ["Piano-right_C6_0.25"], "18.0": ["Piano-right_D6_1.0"], "18.5": ["Piano-right_G5_0.5", "Piano-left_E5_0.5"], "19.0": ["Piano-right_A5.C6_0.5", "Piano-left_F5_0.5"], "19.5": ["Piano-right_C6_0.25", "Piano-right_G#5_0.5", "Piano-left_B4_0.5"], "19.75": ["Piano-right_D6_0.25"], "20.0": ["Piano-right_G5_0.5", "Piano-right_E-6_1.0", "Piano-left_C5_0.5"], "20.5": ["Piano-right_A5_0.5", "Piano-left_F#4_0.5"], "21.0": ["Piano-right_D6.B-5_0.5", "Piano-left_G4_0.5"], "21.5": ["Piano-right_G5_0.5", "Piano-right_D6_0.25", "Piano-left_E-4_0.5"], "21.75": ["Piano-right_E-6_0.25"], "22.0": ["Piano-right_F6_0.75", "Piano-right_F5_0.5", "Piano-left_D4_0.5"], "22.5": ["Piano-right_B-5_0.5", "Piano-left_C#4_0.5"], "22.75": ["Piano-right_G6_0.25"], "23.0": ["Piano-right_F6_0.25", "Piano-right_G5_0.5", "Piano-left_C4_0.5"], "23.25": ["Piano-right_E-6_0.5"], "23.5": ["Piano-right_A5_0.5", "Piano-left_F3_0.5"], "23.75": ["Piano-right_F6_0.25"], "24.0": ["Piano-right_E-6_0.25", "Piano-right_F5_0.5", "Piano-left_B-3_0.5"], "24.25": ["Piano-right_D6_0.5"], "24.5": ["Piano-right_B-5_1.0", "Piano-left_F#3_0.5"], "24.75": ["Piano-right_E-6_0.25"], "25.0": ["Piano-right_D6_0.25", "Piano-left_F3_0.5"], "25.25": ["Piano-right_C6_0.25"], "25.5": ["Piano-right_D6_0.25", "Piano-right_A5.F5_0.5", "Piano-left_E-3_0.5"], "25.75": ["Piano-right_E-6_0.25"], "26.0": ["Piano-right_F5.B-5_0.5", "Piano-right_G6_0.25", "Piano-left_D3_0.5"], "26.25": ["Piano-right_F6_0.25"], "26.5": ["Piano-right_G6_0.25", "Piano-right_B-5_0.5", "Piano-left_C#3_0.5"], "26.75": ["Piano-right_F6_0.25"], "27.0": ["Piano-right_F6_0.25", "Piano-right_G5_0.5", "Piano-left_C3_0.5"], "27.25": ["Piano-right_E-6_0.25"], "27.5": ["Piano-right_A5_0.5", "Piano-right_F6_0.25", "Piano-left_F2_0.5"], "27.75": ["Piano-right_E-6_0.25"], "28.0": ["Piano-right_E-6_0.25", "Piano-right_F5_0.5", "Piano-left_B-2_0.5"], "28.25": ["Piano-right_D6_0.25"], "28.5": ["Piano-right_E-6_0.25", "Piano-right_B-5_1.0", "Piano-left_F#2_0.5"], "28.75": ["Piano-right_D6_0.25"], "29.0": ["Piano-right_D6_0.25", "Piano-left_F2_0.5"], "29.25": ["Piano-right_C6_0.25"], "29.5": ["Piano-right_D6_0.25", "Piano-right_F5.A5_0.5", "Piano-left_E-2_0.5"], "29.75": ["Piano-right_E-6_0.25"], "1.75": ["Piano-left_B-1_0.25"], "2.0": ["Piano-left_D4.F3.B-3_0.75"], "5.75": ["Piano-left_B-1_0.25"], "6.0": ["Piano-left_B-3.F3.D4.F4_0.75"], "30.0": ["Piano-left_D2_0.5"], "30.5": ["Piano-left_C#2_0.5"], "31.0": ["Piano-left_C2_0.5"], "31.5": ["Piano-left_F#1_0.5"], "32.0": ["Piano-left_G1_0.5"], "32.5": ["Piano-left_E-2_0.5"], "33.0": ["Piano-left_F2_0.25"], "33.5": ["Piano-left_F1.F2_0.25"], "34.0": ["Piano-left_B-2.B-1_0.25"], "34.25": ["Piano-left_F3.B-3.D4_0.25"], "34.5": ["Piano-left_D4.B-3.F3_0.25"], "34.75": ["Piano-left_F3.D4.B-3_0.25"], "35.25": ["Piano-left_D4.F3.B-3_0.25"], "35.5": ["Piano-left_B-3.F3.D4_0.25"], "35.75": ["Piano-left_B-3.F3.D4_0.25"], "36.25": ["Piano-left_F3.B-3.D4_0.25"], "36.75": ["Piano-left_B-3.D3_0.25"], "37.25": ["Piano-left_F3.B-3.D4_0.25"], "37.75": ["Piano-left_C4.E-3.B-3_0.25"], "38.0": ["Piano-left_B-2.B-1_0.25"], "38.25": ["Piano-left_B-3.E-4.G3_0.25"], "38.5": ["Piano-left_E-4.G3.B-3_0.25"], "38.75": ["Piano-left_E-4.B-3.G3_0.25"], "39.25": ["Piano-left_B-3.C4.E-3_0.25"], "39.5": ["Piano-left_B-3.C4.E-3_0.25"], "39.75": ["Piano-left_C4.B-3.E-3_0.25"], "40.25": ["Piano-left_B-3.E-4.G3_0.25"], "40.75": ["Piano-left_E3.B-3.C#4_0.25"], "41.25": ["Piano-left_F#3.E-4.B-3_0.25"], "41.75": ["Piano-left_D4.F3.B-3_0.25"], "42.0": ["Piano-left_B-2.B-1_0.25"], "42.25": ["Piano-left_B-3.G#3.F4_0.25"], "42.5": ["Piano-left_F4.G#3.B-3_0.25"], "42.75": ["Piano-left_F4.G#3.B-3_0.25"], "43.25": ["Piano-left_B-3.F3.D4_0.25"], "43.5": ["Piano-left_D4.B-3.F3_0.25"], "43.75": ["Piano-left_B-3.D4.F3_0.25"], "44.25": ["Piano-left_B-3.F4.G#3_0.25"], "44.75": ["Piano-left_B-3.F#3.D4_0.25"], "45.25": ["Piano-left_B-3.F4.G#3_0.25"], "45.75": ["Piano-left_B-3.E-4.G3_0.25"], "46.0": ["Piano-left_B-2.B-1_0.25"], "46.25": ["Piano-left_E-4.G4.B-3_0.25"], "46.5": ["Piano-left_G4.B-3.E-4_0.25"], "46.75": ["Piano-left_G4.B-3.E-4_0.25"], "47.25": ["Piano-left_B-3.E-4.G3_0.25"], "47.5": ["Piano-left_E-4.B-3.G3_0.25"]}, "beethoven_opus22_4.mid": {"1.25": ["Piano-right_F5_0.25"], "1.5": ["Piano-right_G5_0.25"], "1.75": ["Piano-right_F5_0.25"], "2.0": ["Piano-right_E-5_0.25", "Piano-left_B-3_0.5"], "2.25": ["Piano-right_D5_0.25", "Piano-left_F4_0.25"], "2.5": ["Piano-right_C5_0.25", "Piano-left_D4_0.5"], "2.75": ["Piano-right_B-4_0.25", "Piano-left_F4_0.25"], "3.0": ["Piano-right_A4_0.5", "Piano-left_E-4_0.25", "Piano-left_C4_0.5"], "3.5": ["Piano-right_B-4_0.5", "Piano-left_D4_0.25", "Piano-left_B-3_0.5"], "4.0": ["Piano-right_B4_0.5", "Piano-left_A3.E-4_2.0"], "4.5": ["Piano-right_C5_0.75", "Piano-left_F4_0.25"], "5.25": ["Piano-right_F#5_0.25", "Piano-left_F4_0.25"], "5.5": ["Piano-right_A5_0.25", "Piano-left_F4_0.25"], "5.75": ["Piano-right_G5_0.25", "Piano-left_F4_0.25"], "6.0": ["Piano-right_F5_0.25", "Piano-left_A3_0.5"], "6.25": ["Piano-right_E-5_0.25", "Piano-left_F4_0.25"], "6.5": ["Piano-right_D5_0.25", "Piano-left_E-4_0.5"], "6.75": ["Piano-right_C5_0.25", "Piano-left_F4_0.25"], "7.0": ["Piano-right_B-4_0.5", "Piano-left_D4_0.5"], "7.5": ["Piano-right_C5_0.5", "Piano-left_A3_0.5"], "8.0": ["Piano-right_C#5_0.5", "Piano-left_B-3_1.5"], "8.5": ["Piano-right_D5_0.75", "Piano-left_F4_0.25"], "9.25": ["Piano-right_F5_0.25", "Piano-left_F4_0.25"], "9.5": ["Piano-right_G5_0.25", "Piano-left_B3_0.5"], "9.75": ["Piano-right_D5_0.25", "Piano-left_F4_0.25"], "10.0": ["Piano-right_F5_0.25", "Piano-left_C4_0.5"], "10.25": ["Piano-right_E-5_0.25", "Piano-left_F4_0.25"], "10.5": ["Piano-right_F5_0.25", "Piano-left_A3_0.5"], "10.75": ["Piano-right_C5_0.25", "Piano-left_F4_0.25"], "11.0": ["Piano-right_E-5_0.25", "Piano-left_B-3_0.5"], "11.25": ["Piano-right_D5_0.25", "Piano-left_F4_0.25"], "11.5": ["Piano-right_G5_0.25", "Piano-left_B3_0.5"], "11.75": ["Piano-right_D5_0.25", "Piano-left_F4_0.25"], "12.0": ["Piano-right_F5_0.25", "Piano-left_C4_0.5"], "12.25": ["Piano-right_E-5_0.25", "Piano-left_F4_0.25"], "12.5": ["Piano-right_F5_0.25", "Piano-left_A3_0.5"], "12.75": ["Piano-right_C5_0.25", "Piano-left_F4_0.25"], "13.0": ["Piano-right_D5_0.25", "Piano-left_B-3_0.5"], "13.25": ["Piano-right_E-5_0.25", "Piano-left_D4_0.25"], "13.5": ["Piano-right_E5_0.25", "Piano-left_A3_0.5"], "13.75": ["Piano-right_F5_0.25", "Piano-left_C4_0.25"], "14.0": ["Piano-right_F#5_0.25", "Piano-left_G3_0.5"], "14.25": ["Piano-right_G5_0.25", "Piano-left_B-3_0.25"], "14.5": ["Piano-right_A5_0.25", "Piano-left_G3_0.5"], "14.75": ["Piano-right_B-5_0.25", "Piano-left_B-3_0.25"], "15.0": ["Piano-right_C6_0.25", "Piano-left_C3_0.5"], "15.25": ["Piano-right_C#6_0.25", "Piano-left_B-3_0.25"], "15.5": ["Piano-right_D6_0.25", "Piano-left_C3_0.5"], "15.75": ["Piano-right_E5_0.25", "Piano-left_B-3_0.25"], "16.0": ["Piano-right_G5_0.5", "Piano-left_F3_1.5"], "16.5": ["Piano-right_F5_0.5", "Piano-left_A3_0.25"], "17.25": ["Piano-right_F4.F5_0.25"], "17.5": ["Piano-right_G4.G5_0.25"], "17.75": ["Piano-right_F4.F5_0.25"], "18.0": ["Piano-right_E-4.E-5_0.25", "Piano-left_B-2_0.5"], "18.25": ["Piano-right_D4.D5_0.25", "Piano-left_F3_0.25"], "18.5": ["Piano-right_C4.C5_0.25", "Piano-left_D3_0.5"], "18.75": ["Piano-right_B-3.B-4_0.25", "Piano-left_F3_0.25"], "19.0": ["Piano-right_A3.A4_0.5", "Piano-left_E-3_0.25", "Piano-left_C3_0.5"], "19.5": ["Piano-right_B-3.B-4_0.5", "Piano-left_D3_0.25", "Piano-left_B-2_0.5"], "20.0": ["Piano-right_B3.B4_0.5", "Piano-left_A2.E-3_2.0"], "20.5": ["Piano-right_C4.C5_0.75", "Piano-left_F3_0.25"], "21.25": ["Piano-right_F#4.F#5_0.25", "Piano-left_F3_0.25"], "21.5": ["Piano-right_A4.A5_0.25", "Piano-left_F3_0.25"], "21.75": ["Piano-right_G4.G5_0.25", "Piano-left_F3_0.25"], "22.0": ["Piano-right_F4.F5_0.25", "Piano-left_A2_0.5"], "22.25": ["Piano-right_E-4.E-5_0.25", "Piano-left_F3_0.25"], "22.5": ["Piano-right_D4.D5_0.25", "Piano-left_E-3_0.5"], "22.75": ["Piano-right_C4.C5_0.25", "Piano-left_F3_0.25"], "23.0": ["Piano-right_B-3.B-4_0.5", "Piano-left_D3_0.5"], "23.5": ["Piano-right_C4.C5_0.5", "Piano-left_A2_0.5"], "24.0": ["Piano-right_C#4.C#5_0.5", "Piano-left_B-2_1.5"], "24.5": ["Piano-right_D4.D5_0.75", "Piano-left_F3_0.25"], "25.25": ["Piano-right_F5_0.25", "Piano-left_F3_0.25"], "25.5": ["Piano-right_G#4_1.0", "Piano-right_G5_0.25", "Piano-left_B2_0.5"], "25.75": ["Piano-right_D5_0.25", "Piano-left_F3_0.25"], "26.0": ["Piano-right_F5_0.25", "Piano-left_C3_0.5"], "26.25": ["Piano-right_E-5_0.25", "Piano-left_F3_0.25"], "26.5": ["Piano-right_A4_0.5", "Piano-right_F5_0.25", "Piano-left_F2_0.5"], "26.75": ["Piano-right_C5_0.25"], "27.0": ["Piano-right_B-4_0.5", "Piano-right_E-5_0.25"], "27.25": ["Piano-right_D5_0.25"], "27.5": ["Piano-right_G#4_1.0", "Piano-right_G5_0.25"], "27.75": ["Piano-right_D5_0.25"], "28.0": ["Piano-right_F5_0.25"], "28.25": ["Piano-right_E-5_0.25"], "28.5": ["Piano-right_A4_0.5", "Piano-right_F5_0.25"], "28.75": ["Piano-right_C5_0.25"], "29.0": ["Piano-right_B-4.E-5_0.25"], "29.25": ["Piano-right_D4.D5_0.25"], "29.5": ["Piano-right_E-4.E-5_0.25"], "29.75": ["Piano-right_F4.F5_0.25"], "30.0": ["Piano-right_F#4.F#5_0.25"], "30.25": ["Piano-right_G4.G5_0.25"], "30.5": ["Piano-right_A4.A5_0.25"], "3.25": ["Piano-left_F4_0.25"], "3.75": ["Piano-left_F4_0.25"], "4.25": ["Piano-left_F4_0.25"], "4.75": ["Piano-left_F4_0.25"], "5.0": ["Piano-left_F4_0.25"], "7.25": ["Piano-left_F4_0.25"], "7.75": ["Piano-left_F4_0.25"], "8.25": ["Piano-left_F4_0.25"], "8.75": ["Piano-left_F4_0.25"], "9.0": ["Piano-left_F4_0.25"], "16.25": ["Piano-left_B-3_0.25"], "16.75": ["Piano-left_G3_0.25"], "17.0": ["Piano-left_A3_0.5"], "19.25": ["Piano-left_F3_0.25"], "19.75": ["Piano-left_F3_0.25"], "20.25": ["Piano-left_F3_0.25"], "20.75": ["Piano-left_F3_0.25"], "21.0": ["Piano-left_F3_0.25"], "23.25": ["Piano-left_F3_0.25"], "23.75": ["Piano-left_F3_0.25"], "24.25": ["Piano-left_F3_0.25"], "24.75": ["Piano-left_F3_0.25"], "25.0": ["Piano-left_F3_0.25"]}, "beethoven_hammerklavier_3.mid": {"0.0": ["Piano-right_A3_1.5", "Piano-left_A1.A2_1.5"], "1.5": ["Piano-right_C#4_1.5", "Piano-left_C#2.C#3_1.5"], "3.0": ["Piano-right_F#4.C#4_1.5", "Piano-right_C#5.A4_1.0", "Piano-left_F#2.C#3.F#3_1.5"], "4.0": ["Piano-right_A4_0.5"], "4.5": ["Piano-right_C#4.A4_0.5", "Piano-left_F#2.C#3.F#3_0.5"], "5.0": ["Piano-right_C#4.F#4_0.5", "Piano-left_A2.C#3.A3_0.5"], "5.5": ["Piano-right_B3.F4.G#4.C#4_0.5", "Piano-left_G#2.C#3.G#3_0.5"], "6.0": ["Piano-right_A3.F#4.A4.C#4_1.5", "Piano-left_F#2.C#3.F#3_1.5"], "7.5": ["Piano-right_B3.B4.F#4_1.0", "Piano-left_D2.D3_1.0"], "8.5": ["Piano-right_F#4.D4.D5_0.5", "Piano-left_B1.B2_0.5"], "9.0": ["Piano-right_D4.D5.F#4_1.0", "Piano-left_B1.B2_1.0"], "10.0": ["Piano-right_F#4.C#5.C#4_0.5", "Piano-left_A1.A2_0.5"], "10.5": ["Piano-right_F#4.C#5.C#4_0.5", "Piano-left_A1.A2_0.5"], "11.0": ["Piano-right_F4.B4.C#5.F5_0.5", "Piano-left_G#1.G#2_0.5"], "11.5": ["Piano-right_C#5.A4.F#4.F#5_0.5", "Piano-left_F#1.F#2_0.5"], "12.0": ["Piano-right_G#5.C#5.G#4_1.5", "Piano-left_F1.F2_1.5"], "13.5": ["Piano-right_D5.B4.G#4_1.5", "Piano-left_B3.G#3.F3.D4_1.5"], "15.0": ["Piano-right_G#4.B4.D5_1.5", "Piano-left_F1.F2_1.5"], "16.0": ["Piano-right_D4_0.5"], "16.5": ["Piano-right_C#4.A4.C#5_1.0", "Piano-left_F#1.F#2_1.0"], "17.5": ["Piano-right_B3.D4.F4.B4_0.5", "Piano-left_G#1.G#2_0.5"], "18.0": ["Piano-right_B3.D4.F4.B4_1.5", "Piano-left_G#1.G#2_1.5"], "19.5": ["Piano-right_B3.F4.D4.B4_0.5", "Piano-left_G#1.G#2_0.5"], "20.0": ["Piano-right_F#4.A3.C#4.A4_0.5", "Piano-left_A1.A2_0.5"], "20.5": ["Piano-right_G#3.D4.F#4.G#4_0.5", "Piano-left_B1.B2_0.5"], "21.0": ["Piano-right_F#4.G#3.E-4.G#4_1.0", "Piano-left_C2.C3_1.0"], "22.0": ["Piano-right_E-4.G#3.F#4.G#4_0.5", "Piano-left_C2.C3_0.5"], "22.5": ["Piano-right_E-4.F#4.G#3.G#4_0.5", "Piano-left_C2.C3_0.5"], "23.0": ["Piano-right_F#4.E-4.A3.A4_0.5", "Piano-left_C2.C3_0.5"], "23.5": ["Piano-right_F#3.A3.E-4.F#4_0.5", "Piano-left_C2.C3_0.5"], "24.0": ["Piano-right_F#3.A3.F#4_1.5", "Piano-right_E-4_0.5", "Piano-left_C#2.C#3_1.5"], "24.5": ["Piano-right_C4_0.5"], "25.0": ["Piano-right_C#4_0.5"], "25.5": ["Piano-right_G#3.F4.F3.C#4_0.5", "Piano-left_C#2.C#3_0.5"], "26.0": ["Piano-right_G#4_0.5", "Piano-left_C#3.F3.G#3_0.5"], "26.5": ["Piano-right_B4_0.5", "Piano-left_C#3.G#3.B3_0.5"], "27.0": ["Piano-right_D4.B4_1.0", "Piano-right_F4_0.5", "Piano-left_C#3.B3_1.0"], "27.5": ["Piano-right_G#4_0.5"], "28.0": ["Piano-right_C#4.A4.F#4_0.5", "Piano-left_C#3.A3_0.5"], "28.5": ["Piano-right_A4.C#4.F#4_0.5", "Piano-left_C#3.A3_0.5"], "29.0": ["Piano-right_F4.G#4.B3.D4_0.5", "Piano-left_C#3.G#3_0.5"], "29.5": ["Piano-right_F#4.E-4_0.5", "Piano-right_A3_0.25", "Piano-left_C#3.F#3_0.5"], "29.75": ["Piano-right_C4_0.25"], "30.0": ["Piano-right_E-4.F#4.A3.C4_1.0", "Piano-left_C#3.F#3_1.0"], "31.0": ["Piano-right_F4.C#4.G#3_0.5", "Piano-left_C#3.F3_0.5"], "31.5": ["Piano-right_F4_0.5", "Piano-left_C#3_1.0", "Piano-left_F3_0.5"], "32.0": ["Piano-right_G#4_0.5", "Piano-left_G#3_0.5"], "32.5": ["Piano-right_F4.G#4_1.0", "Piano-right_B4_0.25", "Piano-left_G#3.C#3_0.5", "Piano-left_B3_0.25"], "32.75": ["Piano-right_D5_0.25", "Piano-left_D4_0.25"], "33.0": ["Piano-right_B4.D5_1.0", "Piano-left_B3.C#3.D4_1.0"], "33.5": ["Piano-right_F4.G#4_0.5"], "34.0": ["Piano-right_F#4.C#5.A4_0.5", "Piano-left_A3.C#3.C#4_0.5"], "34.5": ["Piano-right_C#5.A4_0.5", "Piano-left_C#3.C#4.A3_0.5"], "34.75": ["Piano-right_F#4_0.25"], "35.0": ["Piano-right_D4.G#4.B4.F4_0.5", "Piano-left_C#3.B3.G#3_0.5"], "35.5": ["Piano-right_C4.F#4.A4.E-4_0.5", "Piano-left_C#3.A3.F#3_0.5"], "36.0": ["Piano-right_F#4.A4_1.0", "Piano-left_F#3.C#3.A3_1.0"], "36.5": ["Piano-right_C4.E-4_0.5"], "37.0": ["Piano-right_C#4.F4.G#4_0.5", "Piano-left_F3.C#3.G#3_0.5"], "37.5": ["Piano-right_G#4.F4.C#4_1.0", "Piano-left_F3.C#3.G#3_1.0"], "38.5": ["Piano-right_E4.G4.C#4_1/3", "Piano-left_G3.E3.C#3.B-3_1/3"], "38.75": ["Piano-right_G4_0.25"], "39.0": ["Piano-right_B5_1.0", "Piano-left_D3.G3.B3_1.5"], "40.0": ["Piano-right_A5_0.5"], "40.5": ["Piano-right_G4_1.5", "Piano-right_G5_1.0", "Piano-left_B3.D4_1.0", "Piano-left_G3_1.5"], "41.5": ["Piano-right_F#5_0.5", "Piano-left_D4_0.5"], "42.0": ["Piano-right_G4_1.5", "Piano-right_E5_1.0", "Piano-left_E4.C4_1.5"], "43.0": ["Piano-right_F#5_0.5"], "43.5": ["Piano-right_G4.G5_1.0", "Piano-left_B3.D4_1.0"], "44.5": ["Piano-right_F#4_0.5", "Piano-left_D4_0.5"], "45.0": ["Piano-right_F#4_0.5", "Piano-left_D4_0.5"], "45.5": ["Piano-right_F#4.A4_0.5", "Piano-left_C#4_0.5"], "46.0": ["Piano-right_F#4.A4.C#5_0.5", "Piano-left_C#3.F#3.A3.C#4_0.5"], "46.5": ["Piano-right_C#5.F4.G#4_1.0", "Piano-left_C#3.F3.G#3.C#4_1.0"], "47.5": ["Piano-right_C#5.G#4.F4_0.5", "Piano-left_C#3.F3.G#3.C#4_0.5"], "48.0": ["Piano-right_G#4.F4.C#5_1.0", "Piano-left_C#3.F3.G#3.C#4_1.0"], "49.0": ["Piano-right_F#4.A4_0.5", "Piano-left_F#3.A3.C#4_0.5"], "49.5": ["Piano-right_F#4.A4_0.5", "Piano-left_F#3.A3.C#4_0.5"], "50.0": ["Piano-right_C#4.F#4_0.5", "Piano-left_A3_0.5"], "50.5": ["Piano-right_G#4.F4_0.25", "Piano-right_C#4_0.5", "Piano-left_G#3.B3_0.25"], "50.75": ["Piano-right_F#4.A4_0.25", "Piano-left_F#3.A3_0.25"], "51.0": ["Piano-right_G#4.B4_1.0", "Piano-left_C#2_3.0"], "51.5": ["Piano-right_D4_0.5", "Piano-left_F2_0.5"], "52.0": ["Piano-right_C#4.F#4.A4_0.5", "Piano-left_F#2_0.5"], "52.5": ["Piano-right_B3.F4.D4_1.0", "Piano-right_A4_0.5", "Piano-left_G#2_0.75"], "53.0": ["Piano-right_G#4_0.5"], "53.5": ["Piano-right_F#4.E-4.A3_0.5", "Piano-left_B2_0.25"], "54.0": ["Piano-right_A3.F#4_0.5", "Piano-right_C#4_1.5", "Piano-left_C#2.C#3_1.75"], "54.5": ["Piano-right_G3.E4_0.5"], "55.0": ["Piano-right_G#3.F4_0.5"], "53.25": ["Piano-left_A2_0.25"], "53.75": ["Piano-left_C3_0.25"], "55.75": ["Piano-left_C#3_0.25"], "56.0": ["Piano-left_F3_0.25"], "56.25": ["Piano-left_G#3_0.25"], "56.5": ["Piano-left_B3_0.25"], "56.75": ["Piano-left_D4_0.25"], "57.0": ["Piano-left_C#2.C#3_0.5"], "57.5": ["Piano-left_F2.C#3.F3_0.5"], "58.0": ["Piano-left_C#3.F#2.F#3_0.5"], "58.5": ["Piano-left_G#2.G#3.C#3_0.75"], "59.25": ["Piano-left_A3.A2_0.25"], "59.5": ["Piano-left_B3.B2_0.25"], "59.75": ["Piano-left_C4.C3_0.25"], "60.0": ["Piano-left_C#3_1.0"], "60.5": ["Piano-left_F#3.A3_0.5"], "61.0": ["Piano-left_F3.C#3.G#3_0.5"], "61.5": ["Piano-left_F3.C#3.G#3_0.5"], "62.0": ["Piano-left_B-3.E3.C#3.G3_0.5"], "62.5": ["Piano-left_D3.G3.B3_0.5"], "63.0": ["Piano-left_B3.G2.D3_1.5"], "64.5": ["Piano-left_G3.B2.D4_1.5"]}, "beethoven_hammerklavier_2.mid": {"1.0": ["Piano-right_D5_1/3", "Piano-left_D4.B-3_1/3"], "4/3": ["Piano-right_A4.F5_0.25", "Piano-left_F3.C4_0.25"], "1.5": ["Piano-right_C5.F5_0.5", "Piano-left_C4.A3_0.5"], "2.0": ["Piano-right_F4.D5_0.25", "Piano-left_D4.B-3_0.25"], "2.5": ["Piano-right_B-4_1/3", "Piano-left_B-3.G3_1/3"], "2.75": ["Piano-right_F#4.D5_0.25", "Piano-left_D3.A3_0.25"], "3.0": ["Piano-right_A4.D5_0.5", "Piano-left_A3.F#3_0.5"], "3.5": ["Piano-right_D4.B-4_0.25", "Piano-left_B-3.G3_0.25"], "4.0": ["Piano-right_G4_1/3", "Piano-left_G3.E-3_1/3"], "13/3": ["Piano-right_D4.B-4_0.25", "Piano-left_B-2.F3_0.25"], "4.5": ["Piano-right_F4.B-4_0.5", "Piano-left_F3.D3_0.5"], "5.0": ["Piano-right_B-3.G4_0.25", "Piano-left_G3.E-3_0.25"], "5.5": ["Piano-right_B-3.G4_1/3", "Piano-left_G3.E-3_1/3"], "5.75": ["Piano-right_E-4.A4_0.25", "Piano-left_C3.F3_0.25"], "6.0": ["Piano-right_E-4.A4_0.5", "Piano-left_F3_0.75", "Piano-left_C3_0.5"], "6.5": ["Piano-right_B-3.B-4_0.25", "Piano-left_D3_0.25"], "7.0": ["Piano-right_F4_0.5", "Piano-right_B-4_1/3", "Piano-left_F3_0.5", "Piano-left_D3_1/3"], "22/3": ["Piano-right_C5_0.25", "Piano-left_A2_0.25"], "7.5": ["Piano-right_F4.C5_0.5", "Piano-left_F3_0.75", "Piano-left_A2_0.5"], "8.0": ["Piano-right_B-4.F4.D5_0.25", "Piano-left_G#2_0.25"], "8.5": ["Piano-right_B-4_0.5", "Piano-right_D5_1/3", "Piano-left_G#2.F3_1/3"], "8.75": ["Piano-right_E-5_0.25", "Piano-left_G2.E-3_0.25"], "9.0": ["Piano-right_B-4.E-5_0.5", "Piano-left_E-3.G2_0.5"], "9.5": ["Piano-right_C#5.B-4.F4.F5_0.25", "Piano-left_C#3.F2_0.25"], "10.0": ["Piano-right_G4.B-4.C5.G5_0.25", "Piano-left_E2.C3_0.25"], "10.5": ["Piano-right_C4.A4.C5_0.25", "Piano-left_F2.F3_0.25"], "11.5": ["Piano-right_D6_1/3", "Piano-left_D5.B-4_1/3"], "11.75": ["Piano-right_A5.F6_0.25", "Piano-left_F4.C5_0.25"], "12.0": ["Piano-right_C6.F6_0.5", "Piano-left_C5.A4_0.5"], "12.5": ["Piano-right_F5.D6_0.25", "Piano-left_D5.B-4_0.25"], "13.0": ["Piano-right_B-5_1/3", "Piano-left_B-4.G4_1/3"], "40/3": ["Piano-right_F#5.D6_0.25", "Piano-left_D4.A4_0.25"], "13.5": ["Piano-right_A5.D6_0.5", "Piano-left_A4.F#4_0.5"], "14.0": ["Piano-right_D5.B-5_0.25", "Piano-left_B-4.G4_0.25"], "14.5": ["Piano-right_G5_1/3", "Piano-left_G4.E-4_1/3"], "14.75": ["Piano-right_D5.B-5_0.25", "Piano-left_B-3.F4_0.25"], "15.0": ["Piano-right_F5.B-5_0.5", "Piano-left_F4.D4_0.5"], "15.5": ["Piano-right_B-4.G5_0.25", "Piano-left_G4.E-4_0.25"], "16.0": ["Piano-right_B-4.G5_1/3", "Piano-left_G4.E-4_1/3"], "49/3": ["Piano-right_E-5.A5_0.25", "Piano-left_C4.F4_0.25"], "16.5": ["Piano-right_E-5.A5_0.5", "Piano-left_F4_0.75", "Piano-left_C4_0.5"], "17.0": ["Piano-right_B-4.B-5_0.25", "Piano-left_D4_0.25"], "17.5": ["Piano-right_F5_0.5", "Piano-right_B-5_1/3", "Piano-left_D5_1/3"], "17.75": ["Piano-right_C6_0.25", "Piano-left_C5.A4_0.25"], "18.0": ["Piano-right_F5.C6_0.5", "Piano-left_C5.A4_0.5"], "18.5": ["Piano-right_F5.D6_0.25", "Piano-left_B-4.G#4_0.25"], "19.0": ["Piano-right_B-5_0.5", "Piano-right_E-6_1/3", "Piano-left_G4_1/3", "Piano-left_B-4_0.5"], "58/3": ["Piano-right_E6_0.25", "Piano-left_F#4_0.25"], "19.5": ["Piano-right_B-5.E6_0.5", "Piano-left_B-4.F#4_0.5"], "20.0": ["Piano-right_A5.F5.F6_0.25", "Piano-left_C5.F4_0.25"], "20.5": ["Piano-right_G5.B-5.E6.G6_0.25", "Piano-left_C3.C4_0.25"], "21.0": ["Piano-right_F5.A5.F6_0.25", "Piano-left_F3.F4_0.25"], "22.0": ["Piano-right_B4.D5_1/3", "Piano-left_F4.F3_1.5"], "67/3": ["Piano-right_D5.F5_0.25"], "22.5": ["Piano-right_D5.F5_0.5"], "23.0": ["Piano-right_B4.D5_0.25"], "23.5": ["Piano-right_B4.D5_1/3", "Piano-left_F3.F2_1.5"], "23.75": ["Piano-right_E-5.G5_0.25"], "24.0": ["Piano-right_E-5.G5_0.5"], "24.5": ["Piano-right_C5.E-5_0.25"], "25.0": ["Piano-right_A4.C5_1/3", "Piano-left_F3.F2_1.5"], "76/3": ["Piano-right_C5.E-5_0.25"], "25.5": ["Piano-right_C5.E-5_0.5"], "26.0": ["Piano-right_A4.C5_0.25"], "26.5": ["Piano-right_A4.C5_1/3", "Piano-left_F2.F1_1.5"], "26.75": ["Piano-right_C#5.F5_0.25"], "27.0": ["Piano-right_D5.F5_0.5"], "27.5": ["Piano-right_B-4.D5_0.25"], "28.0": ["Piano-right_A3.C4_1/3", "Piano-left_F#2.F#1_1.0"], "85/3": ["Piano-right_C4.E-4_0.25"], "28.5": ["Piano-right_C4.E-4_1.0"], "29.5": ["Piano-right_B-3.D4_0.5"], "30.0": ["Piano-right_A3.C4_0.5", "Piano-left_A1.A2_0.5"], "30.5": ["Piano-right_G3.B-3_0.5", "Piano-left_B-1.B-2_0.5"], "31.0": ["Piano-right_F3.A3_1.0", "Piano-left_B1.B2_0.5"], "32.0": ["Piano-right_E3.G3_0.5"], "32.5": ["Piano-right_E-3.C4_1.0", "Piano-right_G3_1.5", "Piano-left_C2_0.5"], "33.5": ["Piano-right_D3.B3_0.5"], "35.5": ["Piano-right_B3_1/3"], "35.75": ["Piano-right_D4_0.25"], "36.0": ["Piano-right_D4_0.5"], "36.5": ["Piano-right_B3_0.25"], "37.0": ["Piano-right_D4_1.25", "Piano-right_B4_1/3", "Piano-left_G2_1/3", "Piano-left_G3_1.25"], "112/3": ["Piano-right_D5_0.25", "Piano-left_B2_0.25"], "37.5": ["Piano-right_D5_0.5", "Piano-left_B2_0.5"], "38.0": ["Piano-right_B4_0.25", "Piano-left_G2_0.25"], "38.5": ["Piano-right_C6_1/3", "Piano-left_C5_1/3"], "38.75": ["Piano-right_E-6_0.25", "Piano-left_E-5_0.25"], "39.0": ["Piano-right_E-6_0.5", "Piano-left_E-5_0.5"], "39.5": ["Piano-right_C6_0.25", "Piano-left_C5_0.25"], "40.0": ["Piano-right_D4.B4_1/3", "Piano-left_G3.G2_1.5"], "121/3": ["Piano-right_F4.D5_0.25"], "40.5": ["Piano-right_F4.D5_0.5"], "41.0": ["Piano-right_D4.B4_0.25"], "29.0": ["Piano-left_G1.G2_1.0"], "31.5": ["Piano-left_C2.C3_1.0"], "33.0": ["Piano-left_G2_1.0"], "41.5": ["Piano-left_C3.C2_1.5"], "43.0": ["Piano-left_F1.F2_1.0"], "44.0": ["Piano-left_F2.F3_0.25"], "44.5": ["Piano-left_B-1.B-2_0.25"], "45.0": ["Piano-left_B-1.B-2_0.25"], "46.0": ["Piano-left_F5.F4_1.5"], "47.5": ["Piano-left_F4.F3_1.5"], "49.0": ["Piano-left_F4.F3_1.5"], "50.5": ["Piano-left_F3.F2_1.5"], "52.0": ["Piano-left_F#3.F#2_1.0"], "53.0": ["Piano-left_F#3.C4.E-4_0.5"], "53.5": ["Piano-left_G3.B-3.D4_0.5"], "54.0": ["Piano-left_A3.C4_0.5"], "54.5": ["Piano-left_B-2.G3.B-3_0.5"], "55.0": ["Piano-left_F3.A3_1.0", "Piano-left_B2_0.5"], "55.5": ["Piano-left_C3_1.0"], "56.0": ["Piano-left_E3.G3_0.5"], "56.5": ["Piano-left_E-3.G3_0.5", "Piano-left_C4_1.0"], "57.0": ["Piano-left_G3_1.0"]}}